[{"name": "Decree No. 1 of 21 March 2020 of President of Georgia on Measures to be Implemented in Connection with Declaration of State of Emergency throughout Whole Territory of Georgia", "jur": "Georgia", "year": "2020", "type": "Regulation", "url": "http://www.fao.org/faolex/results/details/en/c/LEX-FAOC196544", "source": "faolex"}, {"name": "Resolución Nº 193-2020-MINAGRI — Protocolo para la implementación de medidas de vigilancia, prevención y control frente al Covid-19 en la actividad de Titulación de la propiedad agraria y catastro rural.", "jur": "Peru", "year": "2020", "type": "Regulation", "url": "http://www.fao.org/faolex/results/details/en/c/LEX-FAOC201254", "source": "faolex"}, {"name": "Public Health Act, 1994, P-37.1.", "jur": "Canada", "year": "1994", "type": "Legislation", "url": "http://www.fao.org/faolex/results/details/en/c/LEX-FAOC238257", "source": "faolex"}]