[{"name": "The Cultural Heritage (Protection) Act, 2025", "year": "2025", "type": "Legislation", "sector": "General", "url": "http://www.fao.org/faolex/results/details/en/c/LEX-FAOC242223", "source": "faolex"}, {"name": "Antigua & Barbuda - National Adaptation Plan", "year": "2025", "type": "National Adaptation Plan", "sector": "", "url": "https://unfccc.int/sites/default/files/resource/NAP_Antigua_and_Barbuda_2025.pdf", "source": "cclw"}, {"name": "Fourth National Communication to the United Nations Framework Convention on Climate Change", "year": "2025", "type": "National Communication", "sector": "", "url": "https://unfccc.int/sites/default/files/resource/DoE%20Antigua%204NC%20Final.pdf", "source": "cclw"}, {"name": "Special Economic Zone (Amendment) Act (No. 4 of 2024).", "year": "2024", "type": "Legislation", "sector": "Private sector and entrepreneurship", "url": "http://www.fao.org/faolex/results/details/en/c/LEX-FAOC235681", "source": "faolex"}, {"name": "Physical Planning (Amendment) Act (No. 15 of 2024).", "year": "2024", "type": "Legislation", "sector": "Land and soil", "url": "http://www.fao.org/faolex/results/details/en/c/LEX-FAOC235682", "source": "faolex"}, {"name": "Antigua and Barbuda National Adaptation Plan.", "year": "2024", "type": "Policy", "sector": "Climate change", "url": "http://www.fao.org/faolex/results/details/en/c/LEX-FAOC241569", "source": "faolex"}, {"name": "The Finance Administration (Climate Resilience and Development Fund) Regulations (No. 45 of 2023).", "year": "2023", "type": "Regulation", "sector": "Climate change", "url": "http://www.fao.org/faolex/results/details/en/c/LEX-FAOC229051", "source": "faolex"}, {"name": "Registered Land (Amendment) Act (No. 8 of 2023).", "year": "2023", "type": "Legislation", "sector": "Land and soil", "url": "http://www.fao.org/faolex/results/details/en/c/LEX-FAOC229059", "source": "faolex"}, {"name": "Protected Areas on Crown Lands (Declaration of Redonda as a Protected Area) Order (No. 37 of 2023).", "year": "2023", "type": "Regulation", "sector": "Wild species and ecosystems", "url": "http://www.fao.org/faolex/results/details/en/c/LEX-FAOC229068", "source": "faolex"}, {"name": "Non-Citizens Land Holding Regulation Act (OECS CITIZEN) Exemption Order (No. 18 of 2023).", "year": "2023", "type": "Legislation", "sector": "Land and soil", "url": "http://www.fao.org/faolex/results/details/en/c/LEX-FAOC229069", "source": "faolex"}, {"name": "Essential Services (Seafarers as Essential Workers) Order (No. 15 of 2023).", "year": "2023", "type": "Regulation", "sector": "Sea", "url": "http://www.fao.org/faolex/results/details/en/c/LEX-FAOC229070", "source": "faolex"}, {"name": "Environmental Protection Levy (Amendment) Act (No. 6 of 2023).", "year": "2023", "type": "Legislation", "sector": "Environment", "url": "http://www.fao.org/faolex/results/details/en/c/LEX-FAOC229071", "source": "faolex"}, {"name": "Companies (Amendment) Act (No. 4 of 2023).", "year": "2023", "type": "Legislation", "sector": "Private sector and entrepreneurship", "url": "http://www.fao.org/faolex/results/details/en/c/LEX-FAOC229120", "source": "faolex"}, {"name": "Port Authority (Amendment) Act 2023 (No. 1 of 2023).", "year": "2023", "type": "Legislation", "sector": "Sea", "url": "http://www.fao.org/faolex/results/details/en/c/LEX-FAOC231865", "source": "faolex"}, {"name": "National Invasive Alien Species (IAS) Strategy and Action Plan.", "year": "2023", "type": "Policy", "sector": "Wild species and ecosystems", "url": "http://www.fao.org/faolex/results/details/en/c/LEX-FAOC235549", "source": "faolex"}, {"name": "Agricultural Health and Food Safety Policy and Implementation Plan for Antigua and Barbuda.", "year": "2023", "type": "Policy", "sector": "Agricultural and rural development; Food and nutrition", "url": "http://www.fao.org/faolex/results/details/en/c/LEX-FAOC241590", "source": "faolex"}, {"name": "Antigua and Barbuda Country Report. CR (2022)", "year": "2023", "type": "Country Report (Cr)", "sector": "", "url": "https://www.unccd.int/sites/default/files/national-reports/2022/ATG/UNCCD%20SO1%20Report%202022%20ATG.pdf", "source": "cclw"}, {"name": "The Financial Administration (Climate Resilience and Development Fund) Regulations (No. 45 of 2023)", "year": "2023", "type": "Regulation", "sector": "Tourism;Other", "url": "https://laws.gov.ag/wp-content/uploads/2024/02/No.-45-of-2023-Finance-Administration-Climate-Resilence-and-Development-Fund-Regulation.pdf", "source": "cclw"}, {"name": "Delimitation of Marine Space (Government of the United Kingdom of Great Britain and Northern Ireland and the Government of Antigua and Barbuda establishing a boundary between Anguilla and Antigua and Barbuda) Ratification of Agreement Act, No. 3 of 2022.", "year": "2022", "type": "Legislation", "sector": "Sea", "url": "http://www.fao.org/faolex/results/details/en/c/LEX-FAOC212641", "source": "faolex"}, {"name": "The Antigua and Barbuda Labour Code (Amendment) Act, no. 4 of 2022.", "year": "2022", "type": "Legislation", "sector": "Employment", "url": "http://www.fao.org/faolex/results/details/en/c/LEX-FAOC212659", "source": "faolex"}, {"name": "Pesticides and Toxic Chemicals (Amendment) Act 2022 (No. 11 of 2022).", "year": "2022", "type": "Legislation", "sector": "Environment; Cultivated plants", "url": "http://www.fao.org/faolex/results/details/en/c/LEX-FAOC225930", "source": "faolex"}, {"name": "Price Control (Items Essential for the Prevention of COVID-19) Order (No. 8 of 2022).", "year": "2022", "type": "Regulation", "sector": "Health", "url": "http://www.fao.org/faolex/results/details/en/c/LEX-FAOC229067", "source": "faolex"}, {"name": "Social Protection (Amendment) Act 2022 (No. 13 of 2022).", "year": "2022", "type": "Legislation", "sector": "Social protection", "url": "http://www.fao.org/faolex/results/details/en/c/LEX-FAOC231864", "source": "faolex"}, {"name": "Pesticides and Toxic Chemicals Act (Amendment of Schedule1) Regulations, 2022 (S.I. No. 29 of 2022).", "year": "2022", "type": "Regulation", "sector": "Cultivated plants", "url": "http://www.fao.org/faolex/results/details/en/c/LEX-FAOC231866", "source": "faolex"}, {"name": "Fisheries (Seafood) Regulations, 2022 (S.I. No. 47 of 2022).", "year": "2022", "type": "Regulation", "sector": "Food and nutrition", "url": "http://www.fao.org/faolex/results/details/en/c/LEX-FAOC231867", "source": "faolex"}, {"name": "Seafood (Live Lobster) (Technical) Regulations, 2022 (S.I. No. 48 of 2022).", "year": "2022", "type": "Regulation", "sector": "Food and nutrition", "url": "http://www.fao.org/faolex/results/details/en/c/LEX-FAOC231868", "source": "faolex"}, {"name": "Antigua and Barbuda Adaptation Communication. AC1", "year": "2022", "type": "Adaptation Communication", "sector": "", "url": "https://unfccc.int/sites/default/files/ACR/2022-07/ATG%20-%20UNFCCC%20Adaptation%20Communication%20-%202022-06-29%20-%20Final.pdf", "source": "cclw"}, {"name": "Antigua and Barbuda Updated Nationally Determined Contribution for the period 2020 – 2030.", "year": "2021", "type": "Policy", "sector": "Climate change", "url": "http://www.fao.org/faolex/results/details/en/c/LEX-FAOC208476", "source": "faolex"}, {"name": "Special Economic Zone (Amendment) Act, no. 17 of 2021.", "year": "2021", "type": "Legislation", "sector": "Land and soil", "url": "http://www.fao.org/faolex/results/details/en/c/LEX-FAOC212640", "source": "faolex"}, {"name": "Non-citizens Land Holding Regulation (Prescribed Forms) Regulations, Statutory Instrument no. 108 of 2021.", "year": "2021", "type": "Regulation", "sector": "Land and soil", "url": "http://www.fao.org/faolex/results/details/en/c/LEX-FAOC212642", "source": "faolex"}, {"name": "The Standards (Technical Regulations) (Labelling of Pre-Packaged Foods) Regulations. Statutory Instrument no. 33 of 2021.", "year": "2021", "type": "Regulation", "sector": "Food and nutrition", "url": "http://www.fao.org/faolex/results/details/en/c/LEX-FAOC212643", "source": "faolex"}, {"name": "Treaty between the Government of the United Kingdom of Great Britain and Northern Ireland and the Government of Antigua and Barbuda establishing a Maritime Boundary between Anguilla and Antigua and Barbuda.", "year": "2021", "type": "Agreement", "sector": "Sea", "url": "http://www.fao.org/faolex/results/details/en/c/LEX-FAOC213266", "source": "faolex"}, {"name": "Maritime Economy Plan.", "year": "2021", "type": "Policy", "sector": "Sea", "url": "http://www.fao.org/faolex/results/details/en/c/LEX-FAOC223285", "source": "faolex"}, {"name": "Tourism Guest Levy Act No. 13 of 2021.", "year": "2021", "type": "Legislation", "sector": "Private sector and entrepreneurship", "url": "http://www.fao.org/faolex/results/details/en/c/LEX-FAOC229052", "source": "faolex"}, {"name": "Antigua and Barbuda National Youth Policy 2021.", "year": "2021", "type": "Policy", "sector": "Youth", "url": "http://www.fao.org/faolex/results/details/en/c/LEX-FAOC240451", "source": "faolex"}, {"name": "Technical analysis of the first biennial update report of Antigua and Barbuda submitted on 3 March 2020. Summary report by the team of technical experts", "year": "2021", "type": "Technical Analysis Summary Report", "sector": "", "url": "https://unfccc.int/sites/default/files/resource/tasr2020_ATG.pdf", "source": "cclw"}, {"name": "FSV1 record - Antigua and Barbuda", "year": "2021", "type": "Facilitative Sharing Of Views Report", "sector": "", "url": "https://unfccc.int/sites/default/files/resource/FSVR1_ATG.pdf", "source": "cclw"}, {"name": "Antigua and Barbuda First NDC (Updated submission)", "year": "2021", "type": "Nationally Determined Contribution", "sector": "", "url": "https://unfccc.int/sites/default/files/NDC/2022-06/ATG%20-%20UNFCCC%20NDC%20-%202021-09-02%20-%20Final.pdf", "source": "cclw"}, {"name": "Public Health Act (Dangerous Infectious Disease) (Amendment) Regulations, 2020 (S.I. No. 24 of 2020).", "year": "2020", "type": "Regulation", "sector": "Health; Disaster risk management", "url": "http://www.fao.org/faolex/results/details/en/c/LEX-FAOC194569", "source": "faolex"}, {"name": "Public Health Act (Dangerous Infectious Disease) (Amendment)(No. 4) Regulations, 2020.", "year": "2020", "type": "Regulation", "sector": "Health; Disaster risk management", "url": "http://www.fao.org/faolex/results/details/en/c/LEX-FAOC194570", "source": "faolex"}, {"name": "Public Health Act (Dangerous Infectious Disease) Regulations, 2020 (S.I. No. 16 of 2020).", "year": "2020", "type": "Regulation", "sector": "Health; Disaster risk management", "url": "http://www.fao.org/faolex/results/details/en/c/LEX-FAOC194800", "source": "faolex"}, {"name": "Modification to the PHA (Dangerous Infectious Disease) (Amendment) (No. 4) Regulations, 2020 (CBH Notice No. 4 of 2020).", "year": "2020", "type": "Regulation", "sector": "Health", "url": "http://www.fao.org/faolex/results/details/en/c/LEX-FAOC194802", "source": "faolex"}, {"name": "Proclamation of the State of Emergency (S.I. No. 19 of 2020).", "year": "2020", "type": "Regulation", "sector": "Health; Disaster risk management", "url": "http://www.fao.org/faolex/results/details/en/c/LEX-FAOC194803", "source": "faolex"}, {"name": "Social Protection Act No. 22 of 2020.", "year": "2020", "type": "Legislation", "sector": "Social protection", "url": "http://www.fao.org/faolex/results/details/en/c/LEX-FAOC210540", "source": "faolex"}, {"name": "Environmental Social Impact Assessment and Management Plan.", "year": "2020", "type": "Policy", "sector": "Climate change", "url": "http://www.fao.org/faolex/results/details/en/c/LEX-FAOC210935", "source": "faolex"}, {"name": "The Antigua and Barbuda Merchant Shipping (Amendment) Act, no. 24 of 2020.", "year": "2020", "type": "Legislation", "sector": "Sea", "url": "http://www.fao.org/faolex/results/details/en/c/LEX-FAOC212636", "source": "faolex"}, {"name": "The Non-Citizens Land Holding Regulation (Amendment) Act, no. 32 of 2020.", "year": "2020", "type": "Legislation", "sector": "Land and soil", "url": "http://www.fao.org/faolex/results/details/en/c/LEX-FAOC212639", "source": "faolex"}, {"name": "The Antigua and Barbuda Labour Code (Amendment) Act no. 13 of 2020.", "year": "2020", "type": "Legislation", "sector": "Employment", "url": "http://www.fao.org/faolex/results/details/en/c/LEX-FAOC212656", "source": "faolex"}, {"name": "Registered Land (Filing Fees) Order (No. 42 of 2020).", "year": "2020", "type": "Regulation", "sector": "Land and soil", "url": "http://www.fao.org/faolex/results/details/en/c/LEX-FAOC229065", "source": "faolex"}, {"name": "Companies (Amendment) Regulations (No. 43 of 2020).", "year": "2020", "type": "Regulation", "sector": "Private sector and entrepreneurship", "url": "http://www.fao.org/faolex/results/details/en/c/LEX-FAOC229115", "source": "faolex"}, {"name": "Companies (Amendment) Act (No. 17 of 2020).", "year": "2020", "type": "Legislation", "sector": "Private sector and entrepreneurship", "url": "http://www.fao.org/faolex/results/details/en/c/LEX-FAOC229119", "source": "faolex"}, {"name": "Antigua and Barbuda Land Degradation Neutrality Target. LDN-T (2020 Country Commitments)", "year": "2020", "type": "Voluntary Land Degradation Neutrality Targets (Ldn-T)", "sector": "", "url": "https://web.archive.org/web/20240724204216/https://www.unccd.int/sites/default/files/ldn_targets/2020-12/Antigua%20and%20Barbuda_LDN%20Country%20Commitments.pdf", "source": "cclw"}, {"name": "Antigua and Barbuda Biennial Update Report. BUR1", "year": "2020", "type": "Biennial Update Report", "sector": "", "url": "https://unfccc.int/sites/default/files/resource/Antigua%20and%20Barbuda%20-%20UNFCCC%20Biennial%20Update%20Report%201%20-%20Final.pdf", "source": "cclw"}, {"name": "National Inventory Report to BUR 1 Antigua and Barbuda", "year": "2020", "type": "National Inventory Report", "sector": "", "url": "https://unfccc.int/documents/210244", "source": "cclw"}, {"name": "Litter Control and Prevention Act No. 3 of 2019.", "year": "2019", "type": "Legislation", "sector": "Environment", "url": "http://www.fao.org/faolex/results/details/en/c/LEX-FAOC188453", "source": "faolex"}, {"name": "Environmental Protection and Management Act No. 10 of 2019.", "year": "2019", "type": "Legislation", "sector": "Environment; Wild species and ecosystems", "url": "http://www.fao.org/faolex/results/details/en/c/LEX-FAOC192576", "source": "faolex"}, {"name": "Special Economic Zone (Amendment) Act No. 27 of 2019.", "year": "2019", "type": "Legislation", "sector": "Trade", "url": "http://www.fao.org/faolex/results/details/en/c/LEX-FAOC203898", "source": "faolex"}, {"name": "The Free Trade and Processing Zone (Amendment) Act, no. 28 of 2019.", "year": "2019", "type": "Legislation", "sector": "Trade", "url": "http://www.fao.org/faolex/results/details/en/c/LEX-FAOC212629", "source": "faolex"}, {"name": "The Antigua and Barbuda Labour Code (Amendment) (No. 2) Act, no. 26 of 2019.", "year": "2019", "type": "Legislation", "sector": "Employment", "url": "http://www.fao.org/faolex/results/details/en/c/LEX-FAOC212651", "source": "faolex"}, {"name": "The Antigua and Barbuda Labour Code (Amendment) Act, no. 9 of 2019.", "year": "2019", "type": "Legislation", "sector": "Employment", "url": "http://www.fao.org/faolex/results/details/en/c/LEX-FAOC212660", "source": "faolex"}, {"name": "Barbuda Land (Amendment) Act No. 41 of 2017.", "year": "2018", "type": "Legislation", "sector": "Land and soil", "url": "http://www.fao.org/faolex/results/details/en/c/LEX-FAOC188658", "source": "faolex"}, {"name": "Tobacco Control Act No. 17 of 2018.", "year": "2018", "type": "Legislation", "sector": "Health", "url": "http://www.fao.org/faolex/results/details/en/c/LEX-FAOC188661", "source": "faolex"}, {"name": "Public Health (Amendment) Act No. 14 of 2018.", "year": "2018", "type": "Legislation", "sector": "Health", "url": "http://www.fao.org/faolex/results/details/en/c/LEX-FAOC188663", "source": "faolex"}, {"name": "Crown Lands (Regulation) (Amendment) Act No. 6 of 2018.", "year": "2018", "type": "Legislation", "sector": "Land and soil", "url": "http://www.fao.org/faolex/results/details/en/c/LEX-FAOC188664", "source": "faolex"}, {"name": "Non-Citizens Land Holding Regulations (Amendment) Act No. 9 of 2018.", "year": "2018", "type": "Legislation", "sector": "Land and soil", "url": "http://www.fao.org/faolex/results/details/en/c/LEX-FAOC188667", "source": "faolex"}, {"name": "Environmental and social safeguards policy.", "year": "2018", "type": "Policy", "sector": "Environment; Social protection", "url": "http://www.fao.org/faolex/results/details/en/c/LEX-FAOC235545", "source": "faolex"}, {"name": "Gender policy.", "year": "2018", "type": "Policy", "sector": "Gender", "url": "http://www.fao.org/faolex/results/details/en/c/LEX-FAOC235546", "source": "faolex"}, {"name": "External Trade (Shopping Plastic Bags Prohibition) Order, No. 83 of 2017.", "year": "2017", "type": "Regulation", "sector": "Trade", "url": "http://www.fao.org/faolex/results/details/en/c/LEX-FAOC183772", "source": "faolex"}, {"name": "Animal Health Act No. 12 of 2017.", "year": "2017", "type": "Legislation", "sector": "Livestock", "url": "http://www.fao.org/faolex/results/details/en/c/LEX-FAOC188447", "source": "faolex"}, {"name": "Standards Act No. 24 of 2017.", "year": "2017", "type": "Legislation", "sector": "General", "url": "http://www.fao.org/faolex/results/details/en/c/LEX-FAOC188452", "source": "faolex"}, {"name": "Delimitation of Maritime Space (Antigua and Barbuda and the Republic of France in the Caribbean Region) (Ratification of Agreement) Act No. 30 of 2017.", "year": "2017", "type": "Legislation", "sector": "Sea", "url": "http://www.fao.org/faolex/results/details/en/c/LEX-FAOC188660", "source": "faolex"}, {"name": "Public Health (Amendment) Act No. 34 of 2017.", "year": "2017", "type": "Legislation", "sector": "Health", "url": "http://www.fao.org/faolex/results/details/en/c/LEX-FAOC188662", "source": "faolex"}, {"name": "Antigua and Barbuda Merchant Shipping (Amendment) Act No. 31 of 2017.", "year": "2017", "type": "Legislation", "sector": "Sea", "url": "http://www.fao.org/faolex/results/details/en/c/LEX-FAOC188665", "source": "faolex"}, {"name": "Strategy for the Protection of the Environment and the Sustainable Development of Antigua and Barbuda 2017 – 2018.", "year": "2017", "type": "Policy", "sector": "Environment; National development", "url": "http://www.fao.org/faolex/results/details/en/c/LEX-FAOC193606", "source": "faolex"}, {"name": "The Antigua and Barbuda Labour Code (Amendment) Act, no. 19 of 2017.", "year": "2017", "type": "Legislation", "sector": "Employment", "url": "http://www.fao.org/faolex/results/details/en/c/LEX-FAOC212655", "source": "faolex"}, {"name": "Barbuda Land (Amendment) Act, 2016 (No. 12 of 2016).", "year": "2016", "type": "Legislation", "sector": "Land and soil", "url": "http://www.fao.org/faolex/results/details/en/c/LEX-FAOC175089", "source": "faolex"}, {"name": "National Strategic Plan for Health 2016 – 2020.", "year": "2016", "type": "Policy", "sector": "Health", "url": "http://www.fao.org/faolex/results/details/en/c/LEX-FAOC175808", "source": "faolex"}, {"name": "Antigua and Barbuda National Communication. NC3", "year": "2016", "type": "National Communication", "sector": "", "url": "https://unfccc.int/sites/default/files/resource/atgnc3_0.pdf", "source": "cclw"}, {"name": "Antigua and Barbuda First NDC (Archived)", "year": "2016", "type": "Nationally Determined Contribution", "sector": "", "url": "https://unfccc.int/sites/default/files/NDC/2022-06/Antigua%20and%20Barbuda%20First.pdf", "source": "cclw"}, {"name": "Tourism Authority (Amendment) Act (No. 4 of 2015)", "year": "2015", "type": "Legislation", "sector": "Wild species and ecosystems", "url": "http://www.fao.org/faolex/results/details/en/c/LEX-FAOC145952", "source": "faolex"}, {"name": "Renewable Energy Act 2015 (No. 6 of 2015).", "year": "2015", "type": "Legislation", "sector": "Energy", "url": "http://www.fao.org/faolex/results/details/en/c/LEX-FAOC145972", "source": "faolex"}, {"name": "Antigua and Barbuda Merchant Shipping (Amendment) Act, 2014 (No. 15 of 2014).", "year": "2015", "type": "Legislation", "sector": "Sea", "url": "http://www.fao.org/faolex/results/details/en/c/LEX-FAOC150868", "source": "faolex"}, {"name": "Small Craft Act, 2014 (No. 14 of 2015).", "year": "2015", "type": "Legislation", "sector": "Sea", "url": "http://www.fao.org/faolex/results/details/en/c/LEX-FAOC158856", "source": "faolex"}, {"name": "Environmental Protection and Management Act, 2015 (No. 11 of 2015).", "year": "2015", "type": "Legislation", "sector": "Environment; Wild species and ecosystems", "url": "http://www.fao.org/faolex/results/details/en/c/LEX-FAOC173027", "source": "faolex"}, {"name": "Medium Term Development Strategy 2016 to 2020.", "year": "2015", "type": "Policy", "sector": "National development", "url": "http://www.fao.org/faolex/results/details/en/c/LEX-FAOC183242", "source": "faolex"}, {"name": "National Plan of Action for the Conservation and Management of Sharks.", "year": "2015", "type": "Policy", "sector": "Fisheries and aquaculture; Wild species and ecosystems", "url": "http://www.fao.org/faolex/results/details/en/c/LEX-FAOC183259", "source": "faolex"}, {"name": "Antigua & Barbuda’s 2015-2020 National Action Plan: Combatting Desertification, Land Degradation & Drought.", "year": "2015", "type": "Policy", "sector": "Land and soil; Disaster risk management", "url": "http://www.fao.org/faolex/results/details/en/c/LEX-FAOC183494", "source": "faolex"}, {"name": "Antigua and Barbuda's Intended Nationally Determined Contribution.", "year": "2015", "type": "Policy", "sector": "Climate change", "url": "http://www.fao.org/faolex/results/details/en/c/LEX-FAOC188729", "source": "faolex"}, {"name": "Special Economic Zone Act No. 17 of 2015.", "year": "2015", "type": "Legislation", "sector": "Private sector and entrepreneurship", "url": "http://www.fao.org/faolex/results/details/en/c/LEX-FAOC193650", "source": "faolex"}, {"name": "National Policy and Multisectoral Action Plan for the Prevention and Control of Non-Communicable Diseases in Antigua and Barbuda.", "year": "2015", "type": "Policy", "sector": "Health", "url": "http://www.fao.org/faolex/results/details/en/c/LEX-FAOC220923", "source": "faolex"}, {"name": "2015-2020 National Action Plan: Combatting Desertification, Land Degradation & Drought (DLDD)", "year": "2015", "type": "Action Plan", "sector": "Other", "url": "https://www.unccd.int/sites/default/files/2022-09/NAP%202015-20%20ANU.pdf", "source": "cclw"}, {"name": "Environmental Protection and Management Act 11/2015", "year": "2015", "type": "Act", "sector": "Environment;Transport", "url": "https://www.ilo.org/dyn/natlex/docs/ELECTRONIC/102699/124270/F-977987007/ATG102699.pdf", "source": "cclw"}, {"name": "Renewable Energy Act", "year": "2015", "type": "Law", "sector": "Energy", "url": "https://climate-laws.org/rails/active_storage/blobs/eyJfcmFpbHMiOnsibWVzc2FnZSI6IkJBaHBBbUVHIiwiZXhwIjpudWxsLCJwdXIiOiJibG9iX2lkIn19--fe33fe1ae8c7c0e45844a43b70d5d2648ee10436/f", "source": "cclw"}, {"name": "Medium Term Development Strategy 2016-2020", "year": "2015", "type": "Strategy", "sector": "", "url": "https://climate-laws.org/rails/active_storage/blobs/eyJfcmFpbHMiOnsibWVzc2FnZSI6IkJBaHBBcEFGIiwiZXhwIjpudWxsLCJwdXIiOiJibG9iX2lkIn19--55c3381f0ac2983853b948f6c20e8fccd4db5869/f", "source": "cclw"}, {"name": "National Parks (Trading) Regulations 2014 (S.I. No. 9 of 2014).", "year": "2014", "type": "Regulation", "sector": "Wild species and ecosystems", "url": "http://www.fao.org/faolex/results/details/en/c/LEX-FAOC135480", "source": "faolex"}, {"name": "Barbuda (Fisheries) Regulations, 2014 (S.I. No. 33 of 2014).", "year": "2014", "type": "Regulation", "sector": "Fisheries and aquaculture", "url": "http://www.fao.org/faolex/results/details/en/c/LEX-FAOC139374", "source": "faolex"}, {"name": "Barbuda (Coastal Zoning and Management) Regulations, 2014 (S.I. No. 34 of 2014).", "year": "2014", "type": "Regulation", "sector": "Sea; Wild species and ecosystems", "url": "http://www.fao.org/faolex/results/details/en/c/LEX-FAOC139375", "source": "faolex"}, {"name": "Barbuda (National Parks Authority) (Establishment) Regulations, 2014 (S.I. No. 35 of 2014).", "year": "2014", "type": "Regulation", "sector": "Wild species and ecosystems", "url": "http://www.fao.org/faolex/results/details/en/c/LEX-FAOC139376", "source": "faolex"}, {"name": "National Strategic Biodiversity Action Plan 2014-2020.", "year": "2014", "type": "Policy", "sector": "Wild species and ecosystems", "url": "http://www.fao.org/faolex/results/details/en/c/LEX-FAOC154533", "source": "faolex"}, {"name": "Maritime Piracy Act No. 17 of 2013.", "year": "2014", "type": "Legislation", "sector": "Sea", "url": "http://www.fao.org/faolex/results/details/en/c/LEX-FAOC188668", "source": "faolex"}, {"name": "Tourism and Business (Special Incentives) Act No. 22 of 2013.", "year": "2014", "type": "Legislation", "sector": "Private sector and entrepreneurship", "url": "http://www.fao.org/faolex/results/details/en/c/LEX-FAOC188669", "source": "faolex"}, {"name": "Fisheries Regulations, 2013 (S.I. No. 2 of 2013).", "year": "2013", "type": "Regulation", "sector": "Fisheries and aquaculture", "url": "http://www.fao.org/faolex/results/details/en/c/LEX-FAOC122461", "source": "faolex"}, {"name": "Plant Protection Act, 2012 (No. 18 of 2012).", "year": "2013", "type": "Legislation", "sector": "Cultivated plants", "url": "http://www.fao.org/faolex/results/details/en/c/LEX-FAOC126404", "source": "faolex"}, {"name": "Pesticides and Toxic Chemicals (Registration, Licensing and Permit) Regulations, 2013 (S.I. No. 59 of 2013).", "year": "2013", "type": "Regulation", "sector": "Environment", "url": "http://www.fao.org/faolex/results/details/en/c/LEX-FAOC135483", "source": "faolex"}, {"name": "Sustainable Energy Action Plan.", "year": "2013", "type": "Policy", "sector": "Energy", "url": "http://www.fao.org/faolex/results/details/en/c/LEX-FAOC175813", "source": "faolex"}, {"name": "Plan of Action 2013-2014 Zero Hunger Challenge in Antigua and Barbuda.", "year": "2013", "type": "Policy", "sector": "Food and nutrition", "url": "http://www.fao.org/faolex/results/details/en/c/LEX-FAOC175814", "source": "faolex"}, {"name": "Customs (Control and Management) Act No. 3 of 2013.", "year": "2013", "type": "Legislation", "sector": "Trade", "url": "http://www.fao.org/faolex/results/details/en/c/LEX-FAOC188657", "source": "faolex"}, {"name": "CARICOM Regional Organization for Standards and Quality Act No. 12 of 2012.", "year": "2013", "type": "Legislation", "sector": "Trade", "url": "http://www.fao.org/faolex/results/details/en/c/LEX-FAOC188659", "source": "faolex"}, {"name": "Customs (Control and Management) (Amendment) Act No. 8 of 2013.", "year": "2013", "type": "Legislation", "sector": "Trade", "url": "http://www.fao.org/faolex/results/details/en/c/LEX-FAOC188666", "source": "faolex"}, {"name": "Sustainable Energy Action Plan", "year": "2013", "type": "Action Plan", "sector": "Energy", "url": "https://www.oas.org/en/sedi/dsd/energy/doc/eap_antiguabarbuda_web.pdf", "source": "cclw"}, {"name": "National Parks (General) Regulations, 2012 (S.I. No. 48 of 2012).", "year": "2012", "type": "Regulation", "sector": "Wild species and ecosystems", "url": "http://www.fao.org/faolex/results/details/en/c/LEX-FAOC122462", "source": "faolex"}, {"name": "Pharmacy Regulations, 1995 (S.I. No. 45 of 2012).", "year": "2012", "type": "Regulation", "sector": "Livestock; Food and nutrition", "url": "http://www.fao.org/faolex/results/details/en/c/LEX-FAOC125280", "source": "faolex"}, {"name": "Antigua and Barbuda Food and Nutrition Security Policy 2012.", "year": "2012", "type": "Policy", "sector": "Food and nutrition", "url": "http://www.fao.org/faolex/results/details/en/c/LEX-FAOC158521", "source": "faolex"}, {"name": "Patents Act No. 8 of 2012.", "year": "2012", "type": "Legislation", "sector": "Trade", "url": "http://www.fao.org/faolex/results/details/en/c/LEX-FAOC188455", "source": "faolex"}, {"name": "Plant Protection (Notifiable Pest) Order, 2011 (S.I. No. 29 of 2011).", "year": "2011", "type": "Regulation", "sector": "Cultivated plants", "url": "http://www.fao.org/faolex/results/details/en/c/LEX-FAOC103331", "source": "faolex"}, {"name": "Plant Protection (Control of Quarantine Pest) Order, 2011 (S.I. No. 28 of 2011).", "year": "2011", "type": "Regulation", "sector": "Cultivated plants", "url": "http://www.fao.org/faolex/results/details/en/c/LEX-FAOC103332", "source": "faolex"}, {"name": "Merchant Shipping (Registration of Ships) Regulations, 2011 (S.I. No. 52 of 2011).", "year": "2011", "type": "Regulation", "sector": "Sea", "url": "http://www.fao.org/faolex/results/details/en/c/LEX-FAOC106838", "source": "faolex"}, {"name": "Co-operative Societies (Amendment) Act (No. 11 of 2011).", "year": "2011", "type": "Legislation", "sector": "Private sector and entrepreneurship", "url": "http://www.fao.org/faolex/results/details/en/c/LEX-FAOC111712", "source": "faolex"}, {"name": "Merchant Shipping (Vessels in Commercial Use for Sport or Pleasure) Regulations, 2011 (S.I. No. 49 of 2011).", "year": "2011", "type": "Regulation", "sector": "Sea", "url": "http://www.fao.org/faolex/results/details/en/c/LEX-FAOC111717", "source": "faolex"}, {"name": "National Energy Policy of Antigua and Barbuda, 2011.", "year": "2011", "type": "Policy", "sector": "Energy", "url": "http://www.fao.org/faolex/results/details/en/c/LEX-FAOC192702", "source": "faolex"}, {"name": "The Antigua and Barbuda Labour Code (Amendment) Act, no. 8 of 2011.", "year": "2011", "type": "Legislation", "sector": "Employment", "url": "http://www.fao.org/faolex/results/details/en/c/LEX-FAOC212657", "source": "faolex"}, {"name": "Sustainable Island Resource Management Zoning Plan for Antigua and Barbuda (including Redonda).", "year": "2011", "type": "Policy", "sector": "Land and soil", "url": "http://www.fao.org/faolex/results/details/en/c/LEX-FAOC235720", "source": "faolex"}, {"name": "Sustainable Island Resource Management Zoning Plan", "year": "2011", "type": "Plan", "sector": "Agriculture;Transport;Tourism;Industry", "url": "https://climate-laws.org/rails/active_storage/blobs/eyJfcmFpbHMiOnsibWVzc2FnZSI6IkJBaHBBcWdHIiwiZXhwIjpudWxsLCJwdXIiOiJibG9iX2lkIn19--d156e142db3159854cc7d95417d577d0c2dd2e9a/f", "source": "cclw"}, {"name": "National Energy Policy", "year": "2011", "type": "Policy", "sector": "Energy;Transport", "url": "https://climate-laws.org/rails/active_storage/blobs/eyJfcmFpbHMiOnsibWVzc2FnZSI6IkJBaHBBbUFHIiwiZXhwIjpudWxsLCJwdXIiOiJibG9iX2lkIn19--4352fe1c8ad929fefc2e52a7f5c5bfc117b1ca63/f", "source": "cclw"}, {"name": "Co-operative Societies Act (No. 9 of 2010).", "year": "2010", "type": "Legislation", "sector": "Private sector and entrepreneurship", "url": "http://www.fao.org/faolex/results/details/en/c/LEX-FAOC102206", "source": "faolex"}, {"name": "Botanical Gardens Regulations (S.I. No. 15 of 2010).", "year": "2010", "type": "Regulation", "sector": "Cultivated plants", "url": "http://www.fao.org/faolex/results/details/en/c/LEX-FAOC102990", "source": "faolex"}, {"name": "Antigua and Barbuda’s Plan of Action to Prevent, Deter and Eliminate Illegal, Unreported and Unregulated Fishing.", "year": "2010", "type": "Policy", "sector": "Fisheries and aquaculture", "url": "http://www.fao.org/faolex/results/details/en/c/LEX-FAOC159764", "source": "faolex"}, {"name": "Antigua and Barbuda. National Communication (NC). NC 2", "year": "2009", "type": "National Communication", "sector": "", "url": "https://unfccc.int/sites/default/files/resource/antnc2.pdf", "source": "cclw"}, {"name": "Small Business Development Regulations, 2008 (S.I. No. 5 of 2008).", "year": "2008", "type": "Regulation", "sector": "Private sector and entrepreneurship", "url": "http://www.fao.org/faolex/results/details/en/c/LEX-FAOC078076", "source": "faolex"}, {"name": "Shipping (Survey) Regulations, 2008 (No. 30 of 2008).", "year": "2008", "type": "Regulation", "sector": "Sea", "url": "http://www.fao.org/faolex/results/details/en/c/LEX-FAOC084658", "source": "faolex"}, {"name": "Shipping (Small Commercial Vessels) Regulations, 2008 (No. 31 of 2008).", "year": "2008", "type": "Regulation", "sector": "Sea", "url": "http://www.fao.org/faolex/results/details/en/c/LEX-FAOC084659", "source": "faolex"}, {"name": "Shipping (Port State Control) Regulations, 2008 (No. 32 of 2008).", "year": "2008", "type": "Regulation", "sector": "Sea", "url": "http://www.fao.org/faolex/results/details/en/c/LEX-FAOC084660", "source": "faolex"}, {"name": "Tourism Authority Act.", "year": "2008", "type": "Legislation", "sector": "Wild species and ecosystems", "url": "http://www.fao.org/faolex/results/details/en/c/LEX-FAOC084661", "source": "faolex"}, {"name": "Pesticides and Toxic Chemicals Act, 2008 (No. 12 of 2008).", "year": "2008", "type": "Legislation", "sector": "Cultivated plants", "url": "http://www.fao.org/faolex/results/details/en/c/LEX-FAOC084662", "source": "faolex"}, {"name": "Essential Services Act, 2008 (No. 9 of 2008).", "year": "2008", "type": "Legislation", "sector": "Water; Energy; Sea", "url": "http://www.fao.org/faolex/results/details/en/c/LEX-FAOC084854", "source": "faolex"}, {"name": "Economic Partnership Agreement between the CARIFORUM States, of the one part, and the European Community and its Member States, of the other part.", "year": "2008", "type": "Agreement", "sector": "Trade", "url": "http://www.fao.org/faolex/results/details/en/c/LEX-FAOC173849", "source": "faolex"}, {"name": "Registered Land (Amendment) Act (No. 6 of 2007).", "year": "2007", "type": "Legislation", "sector": "Land and soil", "url": "http://www.fao.org/faolex/results/details/en/c/LEX-FAOC075092", "source": "faolex"}, {"name": "Barbuda Land Act, 2007 (No. 23 of 2007).", "year": "2007", "type": "Legislation", "sector": "Land and soil", "url": "http://www.fao.org/faolex/results/details/en/c/LEX-FAOC078070", "source": "faolex"}, {"name": "Antigua and Barbuda Merchant Shipping (Amendment) Act, 2007 (No. 12 of 2007).", "year": "2007", "type": "Legislation", "sector": "Sea", "url": "http://www.fao.org/faolex/results/details/en/c/LEX-FAOC080646", "source": "faolex"}, {"name": "Property Tax (Rates of Tax) Order, 2007 (S.I. No. 10 of 2007).", "year": "2007", "type": "Regulation", "sector": "Land and soil", "url": "http://www.fao.org/faolex/results/details/en/c/LEX-FAOC118776", "source": "faolex"}, {"name": "National Youth Policy of Antigua and Barbuda.", "year": "2007", "type": "Policy", "sector": "Youth", "url": "http://www.fao.org/faolex/results/details/en/c/LEX-FAOC175811", "source": "faolex"}, {"name": "Antigua and Barbuda National Implementation Plan for the management of Persistent Organic Pollutants.", "year": "2007", "type": "Policy", "sector": "Environment", "url": "http://www.fao.org/faolex/results/details/en/c/LEX-FAOC218683", "source": "faolex"}, {"name": "Antigua and Barbuda Merchant Shipping Act, 2006 (No. 1 of 2006).", "year": "2006", "type": "Legislation", "sector": "Sea", "url": "http://www.fao.org/faolex/results/details/en/c/LEX-FAOC068248", "source": "faolex"}, {"name": "Fisheries Act, 2006 (Act No. 22 of 2006).", "year": "2006", "type": "Legislation", "sector": "Fisheries and aquaculture", "url": "http://www.fao.org/faolex/results/details/en/c/LEX-FAOC072806", "source": "faolex"}, {"name": "Property Tax and Valuation Act.", "year": "2006", "type": "Legislation", "sector": "Land and soil", "url": "http://www.fao.org/faolex/results/details/en/c/LEX-FAOC075093", "source": "faolex"}, {"name": "Antigua and Barbuda Merchant Shipping (Amendment) Act, 2006 (No. 9 of 2006).", "year": "2006", "type": "Legislation", "sector": "Sea", "url": "http://www.fao.org/faolex/results/details/en/c/LEX-FAOC080647", "source": "faolex"}, {"name": "Investment Authority Act 2006.", "year": "2006", "type": "Legislation", "sector": "Trade", "url": "http://www.fao.org/faolex/results/details/en/c/LEX-FAOC211006", "source": "faolex"}, {"name": "Investment Authority (Amendment) Act, 2016.", "year": "2006", "type": "Legislation", "sector": "Trade", "url": "http://www.fao.org/faolex/results/details/en/c/LEX-FAOC211008", "source": "faolex"}, {"name": "Investment Authority Act (Amendment) Act, 2017.", "year": "2006", "type": "Legislation", "sector": "Trade", "url": "http://www.fao.org/faolex/results/details/en/c/LEX-FAOC211010", "source": "faolex"}, {"name": "Investment Authority (Amendment) Act 2019.", "year": "2006", "type": "Legislation", "sector": "Trade", "url": "http://www.fao.org/faolex/results/details/en/c/LEX-FAOC211012", "source": "faolex"}, {"name": "Investment Authority (Amendment) (No.2) Act 2019.", "year": "2006", "type": "Legislation", "sector": "Trade", "url": "http://www.fao.org/faolex/results/details/en/c/LEX-FAOC211014", "source": "faolex"}, {"name": "National Solid Waste Management Authority (Amendment) Act, 2005 (No. 6 of 2005).", "year": "2005", "type": "Legislation", "sector": "Environment", "url": "http://www.fao.org/faolex/results/details/en/c/LEX-FAOC069527", "source": "faolex"}, {"name": "National Parks (Amendment) Act, 2004 (No. 11 of 2004).", "year": "2004", "type": "Legislation", "sector": "Wild species and ecosystems", "url": "http://www.fao.org/faolex/results/details/en/c/LEX-FAOC053170", "source": "faolex"}, {"name": "National Economic and Social Council Act, 2004 (No. 18 of 2004).", "year": "2004", "type": "Legislation", "sector": "National development", "url": "http://www.fao.org/faolex/results/details/en/c/LEX-FAOC053176", "source": "faolex"}, {"name": "Administration of Small Estates Act, 2004 (Act No. 12 of 2004).", "year": "2004", "type": "Legislation", "sector": "Land and soil", "url": "http://www.fao.org/faolex/results/details/en/c/LEX-FAOC053177", "source": "faolex"}, {"name": "Antigua and Barbuda Development Bank (Amendment) Act, 2003 (No. 28 of 2003).", "year": "2004", "type": "Legislation", "sector": "National development", "url": "http://www.fao.org/faolex/results/details/en/c/LEX-FAOC070509", "source": "faolex"}, {"name": "Public Utilities (Amendment) Act, 2004 (No. 7 of 2004).", "year": "2004", "type": "Legislation", "sector": "Water", "url": "http://www.fao.org/faolex/results/details/en/c/LEX-FAOC070510", "source": "faolex"}, {"name": "Litter (Amendment) Act (No. 8 of 2004).", "year": "2004", "type": "Legislation", "sector": "Environment", "url": "http://www.fao.org/faolex/results/details/en/c/LEX-FAOC070511", "source": "faolex"}, {"name": "Protocolo al Convenio para el Establecimiento de la Zona de Turismo Sustentable del Caribe (ZTSC).", "year": "2004", "type": "Agreement", "sector": "Environment", "url": "http://www.fao.org/faolex/results/details/en/c/LEX-FAOC092148", "source": "faolex"}, {"name": "Freedom of Information Act No. 19 of 2004.", "year": "2004", "type": "Legislation", "sector": "General", "url": "http://www.fao.org/faolex/results/details/en/c/LEX-FAOC210539", "source": "faolex"}, {"name": "Integrity in Public Life Act No. 23 of 2004.", "year": "2004", "type": "Legislation", "sector": "General", "url": "http://www.fao.org/faolex/results/details/en/c/LEX-FAOC219961", "source": "faolex"}, {"name": "Environmental Management Strategy and Action Plan 2004 to 2009.", "year": "2004", "type": "Policy", "sector": "Environment", "url": "http://www.fao.org/faolex/results/details/en/c/LEX-FAOC233765", "source": "faolex"}, {"name": "Prevention of Corruption Act No. 21 of 2004.", "year": "2004", "type": "Legislation", "sector": "General", "url": "http://www.fao.org/faolex/results/details/en/c/LEX-FAOC219959", "source": "faolex"}, {"name": "Environmental Protection Levy Act, 2002 (No. 22 of 2002).", "year": "2003", "type": "Legislation", "sector": "Environment", "url": "http://www.fao.org/faolex/results/details/en/c/LEX-FAOC037337", "source": "faolex"}, {"name": "Animals (Prevention and Control of Amblyomma Variegatum) Regulations, 2003 (S.I. No. 13 of 2003).", "year": "2003", "type": "Regulation", "sector": "Livestock", "url": "http://www.fao.org/faolex/results/details/en/c/LEX-FAOC043590", "source": "faolex"}, {"name": "Physical Planning Act, 2003 (No. 6 of 2003).", "year": "2003", "type": "Legislation", "sector": "Land and soil", "url": "http://www.fao.org/faolex/results/details/en/c/LEX-FAOC043862", "source": "faolex"}, {"name": "External Trade (Import Prohibition) Order (S.I. No. 16 of 2002).", "year": "2002", "type": "Regulation", "sector": "Trade", "url": "http://www.fao.org/faolex/results/details/en/c/LEX-FAOC034182", "source": "faolex"}, {"name": "Agreement Establishing the Caribbean Regional Fisheries Mechanism.", "year": "2002", "type": "Agreement", "sector": "Fisheries and aquaculture", "url": "http://www.fao.org/faolex/results/details/en/c/LEX-FAOC035822", "source": "faolex"}, {"name": "Disaster Management Act, 2002 (No. 13 of 2002).", "year": "2002", "type": "Legislation", "sector": "Disaster risk management", "url": "http://www.fao.org/faolex/results/details/en/c/LEX-FAOC037339", "source": "faolex"}, {"name": "Antigua and Barbuda Merchant Shipping (Amendment) Act 2002 (No. 19 of 2002).", "year": "2002", "type": "Legislation", "sector": "Sea", "url": "http://www.fao.org/faolex/results/details/en/c/LEX-FAOC045459", "source": "faolex"}, {"name": "Disaster Management Act No. 13/02", "year": "2002", "type": "Act", "sector": "Water", "url": "https://climate-laws.org/rails/active_storage/blobs/eyJfcmFpbHMiOnsibWVzc2FnZSI6IkJBaHBBZ2NGIiwiZXhwIjpudWxsLCJwdXIiOiJibG9iX2lkIn19--c761d667f889063f0464fa8a1a0fd98495b53dee/f", "source": "cclw"}, {"name": "Public Market Complex Act 2001 (No. 11 of 2001).", "year": "2001", "type": "Legislation", "sector": "Livestock; Food and nutrition", "url": "http://www.fao.org/faolex/results/details/en/c/LEX-FAOC027300", "source": "faolex"}, {"name": "Public Market Complex Regulations (No. 32 of 2001).", "year": "2001", "type": "Regulation", "sector": "Food and nutrition", "url": "http://www.fao.org/faolex/results/details/en/c/LEX-FAOC028736", "source": "faolex"}, {"name": "Antigua and Barbuda Merchant Shipping (Amendment) Act 2001 (No. 1 of 2001).", "year": "2001", "type": "Legislation", "sector": "Sea", "url": "http://www.fao.org/faolex/results/details/en/c/LEX-FAOC045458", "source": "faolex"}, {"name": "Convenio para el Establecimiento de la Zona de Turismo Sustentable del Caribe (ZTSC).", "year": "2001", "type": "Agreement", "sector": "Environment", "url": "http://www.fao.org/faolex/results/details/en/c/LEX-FAOC092147", "source": "faolex"}, {"name": "Antigua and Barbuda. National Communication (NC). NC 1", "year": "2001", "type": "National Communication", "sector": "", "url": "https://unfccc.int/sites/default/files/resource/Antigua%20and%20Barbuda%20INC.pdf", "source": "cclw"}, {"name": "Law Revision (Miscellaneous Amendments) (No. 2) Act, 2000 (No. 9 of 2000).", "year": "2000", "type": "Legislation", "sector": "Wild species and ecosystems", "url": "http://www.fao.org/faolex/results/details/en/c/LEX-FAOC070506", "source": "faolex"}, {"name": "Law Revision (Miscellaneous Amendments) (No. 3) Act, 2000 (No. 20 of 2000).", "year": "2000", "type": "Legislation", "sector": "Land and soil", "url": "http://www.fao.org/faolex/results/details/en/c/LEX-FAOC070508", "source": "faolex"}, {"name": "Antigua and Barbuda Merchant Shipping (Amendment) Act 1998 (No. 7 of 1998).", "year": "1998", "type": "Legislation", "sector": "Sea", "url": "http://www.fao.org/faolex/results/details/en/c/LEX-FAOC045457", "source": "faolex"}, {"name": "Wills (Convention on Conflict of Laws) Act (No. 2 of 1998).", "year": "1998", "type": "Legislation", "sector": "Land and soil", "url": "http://www.fao.org/faolex/results/details/en/c/LEX-FAOC070489", "source": "faolex"}, {"name": "The Antigua and Barbuda Labour Code (Amendment) Act, no. 16 of 1998.", "year": "1998", "type": "Legislation", "sector": "Employment", "url": "http://www.fao.org/faolex/results/details/en/c/LEX-FAOC212653", "source": "faolex"}, {"name": "Limitation Act (No. 8 of 1997).", "year": "1997", "type": "Legislation", "sector": "Land and soil", "url": "http://www.fao.org/faolex/results/details/en/c/LEX-FAOC011922", "source": "faolex"}, {"name": "Antigua and Barbuda Merchant Shipping (Amendment) Act 1997 (No. 7 of 1997).", "year": "1997", "type": "Legislation", "sector": "Sea", "url": "http://www.fao.org/faolex/results/details/en/c/LEX-FAOC045456", "source": "faolex"}, {"name": "Noise Abatement Act (No. 10 of 1996).", "year": "1997", "type": "Legislation", "sector": "Environment", "url": "http://www.fao.org/faolex/results/details/en/c/LEX-FAOC070494", "source": "faolex"}, {"name": "Companies Regulations 1997.", "year": "1997", "type": "Regulation", "sector": "Private sector and entrepreneurship", "url": "http://www.fao.org/faolex/results/details/en/c/LEX-FAOC229113", "source": "faolex"}, {"name": "Law Revision (Miscellaneous Amendments) (No. 2) Act, 1995 (No. 17 of 1995).", "year": "1996", "type": "Legislation", "sector": "Sea", "url": "http://www.fao.org/faolex/results/details/en/c/LEX-FAOC006350", "source": "faolex"}, {"name": "Land Development and Control Regulations, 1996 (S.I. No. 20 of 1996).", "year": "1996", "type": "Regulation", "sector": "Land and soil", "url": "http://www.fao.org/faolex/results/details/en/c/LEX-FAOC006727", "source": "faolex"}, {"name": "Companies Act (No. 18 of 1995).", "year": "1996", "type": "Legislation", "sector": "Private sector and entrepreneurship", "url": "http://www.fao.org/faolex/results/details/en/c/LEX-FAOC229112", "source": "faolex"}, {"name": "Oil Pollution of Maritime Areas Act, 1995 (Act No. 14 of 1995).", "year": "1995", "type": "Legislation", "sector": "Sea", "url": "http://www.fao.org/faolex/results/details/en/c/LEX-FAOC006348", "source": "faolex"}, {"name": "National Solid Waste Management Authority Act 1995 (No. 10 of 1995).", "year": "1995", "type": "Legislation", "sector": "Environment", "url": "http://www.fao.org/faolex/results/details/en/c/LEX-FAOC069525", "source": "faolex"}, {"name": "Pharmacy Act, 1995 (No. 11 of 1995).", "year": "1995", "type": "Legislation", "sector": "Livestock; Health", "url": "http://www.fao.org/faolex/results/details/en/c/LEX-FAOC125270", "source": "faolex"}, {"name": "The Free Trade and Processing Zone Act, no. 12 of 1994.", "year": "1994", "type": "Legislation", "sector": "Trade", "url": "http://www.fao.org/faolex/results/details/en/c/LEX-FAOC212628", "source": "faolex"}, {"name": "Animals (Prevention and Control of Amblyomma Variegatum and Associated Diseases) Regulations, 1993.", "year": "1993", "type": "Regulation", "sector": "Livestock", "url": "http://www.fao.org/faolex/results/details/en/c/LEX-FAOC004674", "source": "faolex"}, {"name": "Animals (International Movement and Disease) Regulations, 1993 (S.I. No. 19 of 1993).", "year": "1993", "type": "Regulation", "sector": "Livestock", "url": "http://www.fao.org/faolex/results/details/en/c/LEX-FAOC006349", "source": "faolex"}, {"name": "Beach Protection (Amendment) Act (No. 6 of 1993).", "year": "1993", "type": "Legislation", "sector": "Land and soil; Sea", "url": "http://www.fao.org/faolex/results/details/en/c/LEX-FAOC018145", "source": "faolex"}, {"name": "Protection of Animals (Amendment) Act (No. 5 of 1993).", "year": "1993", "type": "Legislation", "sector": "Livestock", "url": "http://www.fao.org/faolex/results/details/en/c/LEX-FAOC018148", "source": "faolex"}, {"name": "Public Utilities (Amendment) Act (No. 8 of 1993).", "year": "1993", "type": "Legislation", "sector": "Water", "url": "http://www.fao.org/faolex/results/details/en/c/LEX-FAOC070504", "source": "faolex"}, {"name": "Animals (Prescribed Disease) Regulations, 1992 (S.I. No. 22 of 1992).", "year": "1992", "type": "Regulation", "sector": "Livestock", "url": "http://www.fao.org/faolex/results/details/en/c/LEX-FAOC006351", "source": "faolex"}, {"name": "Agreement establishing common fisheries surveillance zones of participating member States of the Organisation of Eastern Caribbean States, 1991.", "year": "1991", "type": "Agreement", "sector": "Fisheries and aquaculture", "url": "http://www.fao.org/faolex/results/details/en/c/LEX-FAOC001087", "source": "faolex"}, {"name": "Fisheries Regulations, 1990.", "year": "1990", "type": "Regulation", "sector": "Fisheries and aquaculture", "url": "http://www.fao.org/faolex/results/details/en/c/LEX-FAOC001012", "source": "faolex"}, {"name": "National Parks (Nelson's Dockyard Parking) Regulations (S.I. 32 of 1989).", "year": "1989", "type": "Regulation", "sector": "Wild species and ecosystems", "url": "http://www.fao.org/faolex/results/details/en/c/LEX-FAOC061395", "source": "faolex"}, {"name": "Ratification of Treaties Act (Cap. 364).", "year": "1989", "type": "Legislation", "sector": "General", "url": "http://www.fao.org/faolex/results/details/en/c/LEX-FAOC214274", "source": "faolex"}, {"name": "Consumer Protection Act (No. 23 of 1987).", "year": "1988", "type": "Legislation", "sector": "Trade", "url": "http://www.fao.org/faolex/results/details/en/c/LEX-FAOC070182", "source": "faolex"}, {"name": "Standards Act (Act No. 3 of 1987).", "year": "1987", "type": "Legislation", "sector": "General", "url": "http://www.fao.org/faolex/results/details/en/c/LEX-FAOC002580", "source": "faolex"}, {"name": "Veterinary Act (No. 42 of 1986).", "year": "1987", "type": "Legislation", "sector": "Livestock", "url": "http://www.fao.org/faolex/results/details/en/c/LEX-FAOC070491", "source": "faolex"}, {"name": "National Parks (Amendment) Act, 1984 (Act No. 3 of 1986).", "year": "1986", "type": "Legislation", "sector": "Wild species and ecosystems", "url": "http://www.fao.org/faolex/results/details/en/c/LEX-FAOC006354", "source": "faolex"}, {"name": "Antigua and Barbuda Merchant Shipping Act, 1985 (No. 1 of 1985).", "year": "1986", "type": "Legislation", "sector": "Sea", "url": "http://www.fao.org/faolex/results/details/en/c/LEX-FAOC045443", "source": "faolex"}, {"name": "Animals (International Movement and Disease) Act 1986 (No. 34 of 1986).", "year": "1986", "type": "Legislation", "sector": "Livestock", "url": "http://www.fao.org/faolex/results/details/en/c/LEX-FAOC045447", "source": "faolex"}, {"name": "Maritime Areas (Closing Lines—Internal Waters) Order (S.I. No. 49/1986).", "year": "1986", "type": "Regulation", "sector": "Sea", "url": "http://www.fao.org/faolex/results/details/en/c/LEX-FAOC231921", "source": "faolex"}, {"name": "Fisheries Act, 1983 (Act No. 14 of 1983).", "year": "1984", "type": "Legislation", "sector": "Fisheries and aquaculture", "url": "http://www.fao.org/faolex/results/details/en/c/LEX-FAOC001011", "source": "faolex"}, {"name": "Litter (Fixed Penalty Procedure) Regulations.", "year": "1984", "type": "Regulation", "sector": "Environment", "url": "http://www.fao.org/faolex/results/details/en/c/LEX-FAOC078852", "source": "faolex"}, {"name": "National Parks Act, 1984 (Act No. 11 of 1984).", "year": "1984", "type": "Legislation", "sector": "Wild species and ecosystems", "url": "http://www.fao.org/faolex/results/details/en/c/LEX-FAOC006353", "source": "faolex"}, {"name": "Litter Act (No. 7 of 1983).", "year": "1983", "type": "Legislation", "sector": "Environment", "url": "http://www.fao.org/faolex/results/details/en/c/LEX-FAOC070312", "source": "faolex"}, {"name": "Maritime Areas Act, 1982 (No. 18 of 1982).", "year": "1982", "type": "Legislation", "sector": "Sea", "url": "http://www.fao.org/faolex/results/details/en/c/LEX-FAOC001009", "source": "faolex"}, {"name": "Territorial Waters Act, 1982 (Act No. 18).", "year": "1982", "type": "Legislation", "sector": "Sea", "url": "http://www.fao.org/faolex/results/details/en/c/LEX-FAOC001010", "source": "faolex"}, {"name": "Cattle Trespass Act (No. 15 of 1982).", "year": "1982", "type": "Legislation", "sector": "Livestock", "url": "http://www.fao.org/faolex/results/details/en/c/LEX-FAOC018142", "source": "faolex"}, {"name": "Caribbean Food Corporation Act (No. 16 of 1981).", "year": "1981", "type": "Legislation", "sector": "Food and nutrition", "url": "http://www.fao.org/faolex/results/details/en/c/LEX-FAOC070128", "source": "faolex"}, {"name": "Non-citizens Undeveloped Land Tax Act (No. 14 of 1978).", "year": "1980", "type": "Legislation", "sector": "Land and soil", "url": "http://www.fao.org/faolex/results/details/en/c/LEX-FAOC070319", "source": "faolex"}, {"name": "Antigua and Barbuda Agricultural Development Corporation Act (No. 11 of 1978).", "year": "1979", "type": "Legislation", "sector": "Agricultural and rural development", "url": "http://www.fao.org/faolex/results/details/en/c/LEX-FAOC069701", "source": "faolex"}, {"name": "Antigua and Barbuda Sugar Industry Corporation Act (No. 5 of 1979).", "year": "1979", "type": "Legislation", "sector": "Agricultural and rural development; Cultivated plants", "url": "http://www.fao.org/faolex/results/details/en/c/LEX-FAOC070123", "source": "faolex"}, {"name": "Fisheries (Protection of Lobster) Regulations.", "year": "1978", "type": "Regulation", "sector": "Fisheries and aquaculture", "url": "http://www.fao.org/faolex/results/details/en/c/LEX-FAOC030608", "source": "faolex"}, {"name": "Fisheries (Restriction on Methods of Freshwater Fishing) Regulations (S.R.O. 4/1978).", "year": "1978", "type": "Regulation", "sector": "Fisheries and aquaculture", "url": "http://www.fao.org/faolex/results/details/en/c/LEX-FAOC045483", "source": "faolex"}, {"name": "Fisheries (Restriction on Methods of Saltwater Fishing) Regulations (S.R.O. 5/1978).", "year": "1978", "type": "Regulation", "sector": "Fisheries and aquaculture", "url": "http://www.fao.org/faolex/results/details/en/c/LEX-FAOC045484", "source": "faolex"}, {"name": "Fisheries (Restriction on Taking of Channel Catfish) Notice (S.R.O. 6/1978).", "year": "1978", "type": "Regulation", "sector": "Fisheries and aquaculture", "url": "http://www.fao.org/faolex/results/details/en/c/LEX-FAOC045485", "source": "faolex"}, {"name": "Land Development and Control Act 1977 (Act No. 15 of 1977).", "year": "1977", "type": "Legislation", "sector": "Land and soil", "url": "http://www.fao.org/faolex/results/details/en/c/LEX-FAOC006352", "source": "faolex"}, {"name": "Land Surveyors Regulations (S.R.O. 16/1977).", "year": "1977", "type": "Regulation", "sector": "Land and soil", "url": "http://www.fao.org/faolex/results/details/en/c/LEX-FAOC231922", "source": "faolex"}, {"name": "Land Development (Interim Control) Regulations (S.I. 7/1977).", "year": "1977", "type": "Regulation", "sector": "Land and soil", "url": "http://www.fao.org/faolex/results/details/en/c/LEX-FAOC231923", "source": "faolex"}, {"name": "Beach Control (Prevention of Danger) Regulations.", "year": "1976", "type": "Regulation", "sector": "Sea", "url": "http://www.fao.org/faolex/results/details/en/c/LEX-FAOC061389", "source": "faolex"}, {"name": "Development Fund Act (No. 6 of 1976).", "year": "1976", "type": "Legislation", "sector": "National development", "url": "http://www.fao.org/faolex/results/details/en/c/LEX-FAOC070192", "source": "faolex"}, {"name": "Barbuda Local Government Act, Cap. 44.", "year": "1976", "type": "Legislation", "sector": "General", "url": "http://www.fao.org/faolex/results/details/en/c/LEX-FAOC176344", "source": "faolex"}, {"name": "Registered Land Act (No. 17 of 1975).", "year": "1975", "type": "Legislation", "sector": "Land and soil", "url": "http://www.fao.org/faolex/results/details/en/c/LEX-FAOC045444", "source": "faolex"}, {"name": "Importation of Live Fish Act (No. 23 of 1975).", "year": "1975", "type": "Legislation", "sector": "Food and nutrition", "url": "http://www.fao.org/faolex/results/details/en/c/LEX-FAOC045446", "source": "faolex"}, {"name": "Dumping at Sea Act (No. 29 of 1975).", "year": "1975", "type": "Legislation", "sector": "Sea", "url": "http://www.fao.org/faolex/results/details/en/c/LEX-FAOC070193", "source": "faolex"}, {"name": "Land Adjudication Act (Act No. 16 of 1975).", "year": "1975", "type": "Legislation", "sector": "Land and soil", "url": "http://www.fao.org/faolex/results/details/en/c/LEX-FAOC070294", "source": "faolex"}, {"name": "Land Surveyors Act (No. 15 of 1975).", "year": "1975", "type": "Legislation", "sector": "Land and soil", "url": "http://www.fao.org/faolex/results/details/en/c/LEX-FAOC070303", "source": "faolex"}, {"name": "The Antigua and Barbuda Labour Code Act, chapter 27.", "year": "1975", "type": "Legislation", "sector": "Employment", "url": "http://www.fao.org/faolex/results/details/en/c/LEX-FAOC212644", "source": "faolex"}, {"name": "Proclamation dated 24th of May, 1974 made under section 13 of the Wild Birds Protection Act (S.R.O. No. 26/1974).", "year": "1974", "type": "Miscellaneous", "sector": "Wild species and ecosystems", "url": "http://www.fao.org/faolex/results/details/en/c/LEX-FAOC018162", "source": "faolex"}, {"name": "Antigua and Barbuda Development Bank Act.", "year": "1974", "type": "Legislation", "sector": "General", "url": "http://www.fao.org/faolex/results/details/en/c/LEX-FAOC069703", "source": "faolex"}, {"name": "Central Marketing Corporation Act (No. 14 of 1973).", "year": "1974", "type": "Legislation", "sector": "Agricultural and rural development", "url": "http://www.fao.org/faolex/results/details/en/c/LEX-FAOC070129", "source": "faolex"}, {"name": "Registration of Condominium Titles Act (No. 8 of 1973).", "year": "1974", "type": "Legislation", "sector": "Land and soil", "url": "http://www.fao.org/faolex/results/details/en/c/LEX-FAOC070423", "source": "faolex"}, {"name": "Marine Areas (Preservation and Enhancement) Regulations, 1973 (No. 25 of 1973).", "year": "1973", "type": "Regulation", "sector": "Wild species and ecosystems", "url": "http://www.fao.org/faolex/results/details/en/c/LEX-FAOC001014", "source": "faolex"}, {"name": "Pesticides Control Act, 1973 (Act No. 15 of 1973).", "year": "1973", "type": "Legislation", "sector": "Cultivated plants", "url": "http://www.fao.org/faolex/results/details/en/c/LEX-FAOC038187", "source": "faolex"}, {"name": "Port Authority Act (Act No. 9 of 1973).", "year": "1973", "type": "Legislation", "sector": "Sea", "url": "http://www.fao.org/faolex/results/details/en/c/LEX-FAOC045445", "source": "faolex"}, {"name": "Public Utilities Act (No. 10 of 1973).", "year": "1973", "type": "Legislation", "sector": "Water", "url": "http://www.fao.org/faolex/results/details/en/c/LEX-FAOC070371", "source": "faolex"}, {"name": "Marine Areas (Preservation and Enhancement) Act 1972 (Act No. 5 of 1972).", "year": "1972", "type": "Legislation", "sector": "Wild species and ecosystems", "url": "http://www.fao.org/faolex/results/details/en/c/LEX-FAOC001013", "source": "faolex"}, {"name": "Lands of Antigua and Barbuda Sugar Factory Limited and the Antigua and Barbuda Syndicate Estates Limited (Vesting) Act (No. 32 of 1969).", "year": "1969", "type": "Legislation", "sector": "Land and soil", "url": "http://www.fao.org/faolex/results/details/en/c/LEX-FAOC070305", "source": "faolex"}, {"name": "Non-citizens Land Holding Regulation Act (No. 17 of 1968).", "year": "1968", "type": "Legislation", "sector": "Land and soil", "url": "http://www.fao.org/faolex/results/details/en/c/LEX-FAOC070318", "source": "faolex"}, {"name": "Emergency Powers Act (No. 35 of 1967).", "year": "1967", "type": "Legislation", "sector": "Disaster risk management", "url": "http://www.fao.org/faolex/results/details/en/c/LEX-FAOC070256", "source": "faolex"}, {"name": "Land Sales Duty Act 1977 (Act No. 13 of 1964).", "year": "1965", "type": "Legislation", "sector": "Land and soil", "url": "http://www.fao.org/faolex/results/details/en/c/LEX-FAOC070295", "source": "faolex"}, {"name": "Public Parks Act (Act No. 4 of 1965).", "year": "1965", "type": "Legislation", "sector": "Wild species and ecosystems", "url": "http://www.fao.org/faolex/results/details/en/c/LEX-FAOC070369", "source": "faolex"}, {"name": "Assessment of Compensation (Land of Alvan Camacho) Act (No. 8 of 1962).", "year": "1962", "type": "Legislation", "sector": "Land and soil", "url": "http://www.fao.org/faolex/results/details/en/c/LEX-FAOC070125", "source": "faolex"}, {"name": "Beach Control Act (Cap. 45).", "year": "1959", "type": "Legislation", "sector": "Land and soil", "url": "http://www.fao.org/faolex/results/details/en/c/LEX-FAOC045455", "source": "faolex"}, {"name": "External Trade Act (Cap. 163), Act No. 16 of 1958.", "year": "1958", "type": "Legislation", "sector": "Trade", "url": "http://www.fao.org/faolex/results/details/en/c/LEX-FAOC183768", "source": "faolex"}, {"name": "Distribution and Price of Goods Act (CAP. 138).", "year": "1958", "type": "Legislation", "sector": "Food and nutrition", "url": "http://www.fao.org/faolex/results/details/en/c/LEX-FAOC229066", "source": "faolex"}, {"name": "Land Acquisition Act, CAP. 233", "year": "1958", "type": "Legislation", "sector": "Land and soil", "url": "http://www.fao.org/faolex/results/details/en/c/LEX-FAOC070293", "source": "faolex"}, {"name": "Beach Protection Act.", "year": "1957", "type": "Legislation", "sector": "Land and soil; Sea", "url": "http://www.fao.org/faolex/results/details/en/c/LEX-FAOC018144", "source": "faolex"}, {"name": "Emergency Powers (Hurricane, Earthquake, Fire or Flood) Act (No. 5 of 1957).", "year": "1957", "type": "Legislation", "sector": "Disaster risk management", "url": "http://www.fao.org/faolex/results/details/en/c/LEX-FAOC070257", "source": "faolex"}, {"name": "Emergency Powers (Hurricane, Earthquake, Fire or Flood) Act No. 5/57", "year": "1957", "type": "Act", "sector": "Water", "url": "https://climate-laws.org/rails/active_storage/blobs/eyJfcmFpbHMiOnsibWVzc2FnZSI6IkJBaHBBZ1lGIiwiZXhwIjpudWxsLCJwdXIiOiJibG9iX2lkIn19--6b14d714abf250a5e5b0871c0542bf1b7d52cdce/f", "source": "cclw"}, {"name": "Cotton Export Act (No. 12 of 1954).", "year": "1955", "type": "Legislation", "sector": "Cultivated plants", "url": "http://www.fao.org/faolex/results/details/en/c/LEX-FAOC070183", "source": "faolex"}, {"name": "Land Settlement and Development Board Act (No. 14 of 1953).", "year": "1954", "type": "Legislation", "sector": "Land and soil", "url": "http://www.fao.org/faolex/results/details/en/c/LEX-FAOC070299", "source": "faolex"}, {"name": "Praedial Larcency Act (No. 6 of 1954).", "year": "1954", "type": "Legislation", "sector": "Livestock; Cultivated plants", "url": "http://www.fao.org/faolex/results/details/en/c/LEX-FAOC070365", "source": "faolex"}, {"name": "Animal (Diseases and Importation) Act (No. 31 of 1953).", "year": "1953", "type": "Legislation", "sector": "Livestock", "url": "http://www.fao.org/faolex/results/details/en/c/LEX-FAOC069702", "source": "faolex"}, {"name": "Administration of Insolvent Estates Act.", "year": "1953", "type": "Legislation", "sector": "Land and soil", "url": "http://www.fao.org/faolex/results/details/en/c/LEX-FAOC069704", "source": "faolex"}, {"name": "Antibiotics and Therapeutic Substances Act (Chapter 17).", "year": "1950", "type": "Legislation", "sector": "Livestock", "url": "http://www.fao.org/faolex/results/details/en/c/LEX-FAOC210445", "source": "faolex"}, {"name": "Minerals (Vesting) Act (No. 1 of 1949).", "year": "1949", "type": "Legislation", "sector": "Mineral resources", "url": "http://www.fao.org/faolex/results/details/en/c/LEX-FAOC070316", "source": "faolex"}, {"name": "Town and Country Planning Ordinance.", "year": "1948", "type": "Legislation", "sector": "Land and soil", "url": "http://www.fao.org/faolex/results/details/en/c/LEX-FAOC018188", "source": "faolex"}, {"name": "Radio-active Minerals Act (No. 6 of 1948).", "year": "1948", "type": "Legislation", "sector": "Mineral resources", "url": "http://www.fao.org/faolex/results/details/en/c/LEX-FAOC070374", "source": "faolex"}, {"name": "Sugar Export Cess Act (No. 10 of 1947).", "year": "1947", "type": "Legislation", "sector": "Agricultural and rural development", "url": "http://www.fao.org/faolex/results/details/en/c/LEX-FAOC070487", "source": "faolex"}, {"name": "Watercourses and Waterworks Ordinance.", "year": "1945", "type": "Legislation", "sector": "Water", "url": "http://www.fao.org/faolex/results/details/en/c/LEX-FAOC006355", "source": "faolex"}, {"name": "Antigua and Barbuda Survey Act (No. 2 of 1945).", "year": "1945", "type": "Legislation", "sector": "Land and soil", "url": "http://www.fao.org/faolex/results/details/en/c/LEX-FAOC070124", "source": "faolex"}, {"name": "Intestates Estates Act (No. 4 of 1945).", "year": "1945", "type": "Legislation", "sector": "Land and soil", "url": "http://www.fao.org/faolex/results/details/en/c/LEX-FAOC070292", "source": "faolex"}, {"name": "Larcency Act (No. 24 of 1944).", "year": "1944", "type": "Legislation", "sector": "Livestock; Cultivated plants", "url": "http://www.fao.org/faolex/results/details/en/c/LEX-FAOC070505", "source": "faolex"}, {"name": "Larceny Act (Cap. 241).", "year": "1944", "type": "Legislation", "sector": "Gender", "url": "http://www.fao.org/faolex/results/details/en/c/LEX-FAOC210252", "source": "faolex"}, {"name": "Forestry Act (No. 7 of 1941).", "year": "1941", "type": "Legislation", "sector": "Forestry", "url": "http://www.fao.org/faolex/results/details/en/c/LEX-FAOC018153", "source": "faolex"}, {"name": "Forestry Regulations (Cap. 178).", "year": "1941", "type": "Regulation", "sector": "Forestry", "url": "http://www.fao.org/faolex/results/details/en/c/LEX-FAOC018155", "source": "faolex"}, {"name": "Cotton Traffic Act (No. 10 of 1941).", "year": "1941", "type": "Legislation", "sector": "Cultivated plants", "url": "http://www.fao.org/faolex/results/details/en/c/LEX-FAOC070189", "source": "faolex"}, {"name": "Plant Protection Act (No. 14 of 1941).", "year": "1941", "type": "Legislation", "sector": "Cultivated plants", "url": "http://www.fao.org/faolex/results/details/en/c/LEX-FAOC070364", "source": "faolex"}, {"name": "Slaughter of Cattle Control Act (No. 9 of 1941).", "year": "1941", "type": "Legislation", "sector": "Livestock", "url": "http://www.fao.org/faolex/results/details/en/c/LEX-FAOC070426", "source": "faolex"}, {"name": "Land Settlement Act (No. 15 of 1939).", "year": "1939", "type": "Legislation", "sector": "Land and soil", "url": "http://www.fao.org/faolex/results/details/en/c/LEX-FAOC070298", "source": "faolex"}, {"name": "Employment of Children Prohibition Act (Cap. 151), No. 5 of 1939.", "year": "1939", "type": "Legislation", "sector": "Social protection; Youth", "url": "http://www.fao.org/faolex/results/details/en/c/LEX-FAOC183769", "source": "faolex"}, {"name": "Sugar Quotas Act (No. 16 of 1937).", "year": "1937", "type": "Legislation", "sector": "Trade", "url": "http://www.fao.org/faolex/results/details/en/c/LEX-FAOC070492", "source": "faolex"}, {"name": "Cotton Growers Association Act (No. 16 of 1936).", "year": "1936", "type": "Legislation", "sector": "Cultivated plants", "url": "http://www.fao.org/faolex/results/details/en/c/LEX-FAOC070185", "source": "faolex"}, {"name": "Protection of Animals Act (No. 10 of 1935).", "year": "1935", "type": "Legislation", "sector": "Livestock", "url": "http://www.fao.org/faolex/results/details/en/c/LEX-FAOC018147", "source": "faolex"}, {"name": "Boats Regulation Act (No. 10 of 1933).", "year": "1933", "type": "Legislation", "sector": "Sea", "url": "http://www.fao.org/faolex/results/details/en/c/LEX-FAOC070126", "source": "faolex"}, {"name": "Cotton Export Levy Act (No. 9 of 1933).", "year": "1933", "type": "Legislation", "sector": "Cultivated plants", "url": "http://www.fao.org/faolex/results/details/en/c/LEX-FAOC070184", "source": "faolex"}, {"name": "Cotton Seed Control Act (No. 10 of 1932).", "year": "1932", "type": "Legislation", "sector": "Cultivated plants", "url": "http://www.fao.org/faolex/results/details/en/c/LEX-FAOC070188", "source": "faolex"}, {"name": "Cotton Planting (Regulation) Act (No. 1 of 1931).", "year": "1931", "type": "Legislation", "sector": "Cultivated plants", "url": "http://www.fao.org/faolex/results/details/en/c/LEX-FAOC070186", "source": "faolex"}, {"name": "Real Representative Act (No. 7 of 1928).", "year": "1928", "type": "Legislation", "sector": "Land and soil", "url": "http://www.fao.org/faolex/results/details/en/c/LEX-FAOC070422", "source": "faolex"}, {"name": "Turtle Act (No. 17 of 1927).", "year": "1927", "type": "Legislation", "sector": "Wild species and ecosystems", "url": "http://www.fao.org/faolex/results/details/en/c/LEX-FAOC018187", "source": "faolex"}, {"name": "Cotton Protection Act (No. 7 of 1922).", "year": "1922", "type": "Legislation", "sector": "Cultivated plants", "url": "http://www.fao.org/faolex/results/details/en/c/LEX-FAOC070187", "source": "faolex"}, {"name": "Produce Protection Act (No. 16 of 1929).", "year": "1922", "type": "Legislation", "sector": "Cultivated plants", "url": "http://www.fao.org/faolex/results/details/en/c/LEX-FAOC070367", "source": "faolex"}, {"name": "Crown Lands (Regulation) Act (No. 5 of 1917).", "year": "1917", "type": "Legislation", "sector": "Land and soil", "url": "http://www.fao.org/faolex/results/details/en/c/LEX-FAOC070190", "source": "faolex"}, {"name": "Wild Birds Protection Act (No. 3 of 1913).", "year": "1913", "type": "Legislation", "sector": "Wild species and ecosystems", "url": "http://www.fao.org/faolex/results/details/en/c/LEX-FAOC018161", "source": "faolex"}, {"name": "Fumigation of Plants Act (No. 5 of 1905).", "year": "1905", "type": "Legislation", "sector": "Cultivated plants", "url": "http://www.fao.org/faolex/results/details/en/c/LEX-FAOC070258", "source": "faolex"}, {"name": "Mongoose Prohibition (Barbuda) Act (No. 7 of 1903).", "year": "1903", "type": "Legislation", "sector": "Wild species and ecosystems", "url": "http://www.fao.org/faolex/results/details/en/c/LEX-FAOC018156", "source": "faolex"}, {"name": "Bush Fires Act (No. 5 of 1901).", "year": "1901", "type": "Legislation", "sector": "Forestry", "url": "http://www.fao.org/faolex/results/details/en/c/LEX-FAOC018143", "source": "faolex"}, {"name": "Botanical Gardens Act (No. 12 of 1900).", "year": "1900", "type": "Legislation", "sector": "Cultivated plants", "url": "http://www.fao.org/faolex/results/details/en/c/LEX-FAOC070127", "source": "faolex"}, {"name": "Partition Act (No. 15 of 1895).", "year": "1895", "type": "Legislation", "sector": "Land and soil", "url": "http://www.fao.org/faolex/results/details/en/c/LEX-FAOC070362", "source": "faolex"}, {"name": "Settled Estates Act (CAP. 398).", "year": "1895", "type": "Legislation", "sector": "Land and soil", "url": "http://www.fao.org/faolex/results/details/en/c/LEX-FAOC070425", "source": "faolex"}, {"name": "Small Tenements Act (No. 13 of 1891).", "year": "1892", "type": "Legislation", "sector": "Land and soil", "url": "http://www.fao.org/faolex/results/details/en/c/LEX-FAOC070428", "source": "faolex"}, {"name": "Small Trespass Act (No. 12 of 1891).", "year": "1892", "type": "Legislation", "sector": "Livestock; Land and soil", "url": "http://www.fao.org/faolex/results/details/en/c/LEX-FAOC070429", "source": "faolex"}, {"name": "Importation Prohibition (Epidemic Diseases) Act (No. 1 of 1888).", "year": "1888", "type": "Legislation", "sector": "Livestock", "url": "http://www.fao.org/faolex/results/details/en/c/LEX-FAOC070259", "source": "faolex"}, {"name": "Real Estate Charges Act (Act No. 14 of 1887).", "year": "1887", "type": "Legislation", "sector": "Land and soil", "url": "http://www.fao.org/faolex/results/details/en/c/LEX-FAOC070420", "source": "faolex"}, {"name": "Title by Registration Act (No. 1 of 1886).", "year": "1887", "type": "Legislation", "sector": "Land and soil", "url": "http://www.fao.org/faolex/results/details/en/c/LEX-FAOC070488", "source": "faolex"}, {"name": "Real Property Limitation Act (Act No. 11 of 1877).", "year": "1883", "type": "Legislation", "sector": "Land and soil", "url": "http://www.fao.org/faolex/results/details/en/c/LEX-FAOC070421", "source": "faolex"}, {"name": "Malicious Damage Act (No. 9 of 1876).", "year": "1878", "type": "Legislation", "sector": "Cultivated plants; General", "url": "http://www.fao.org/faolex/results/details/en/c/LEX-FAOC070314", "source": "faolex"}, {"name": "Trustees and Mortgagees Act (No. 10 of 1877).", "year": "1877", "type": "Legislation", "sector": "Land and soil", "url": "http://www.fao.org/faolex/results/details/en/c/LEX-FAOC070496", "source": "faolex"}, {"name": "Real Property Act (Act No. 6 of 1873).", "year": "1873", "type": "Legislation", "sector": "Land and soil", "url": "http://www.fao.org/faolex/results/details/en/c/LEX-FAOC070419", "source": "faolex"}]