[{"name": "Directive Cantonale de Vaud sur la protection des sols sur les chantiers (DMP 863, 2019)", "year": "2019", "type": "Regulation", "sector": "Land and soil", "sub": "Vaud", "url": "http://www.fao.org/faolex/results/details/en/c/LEX-FAOC197078", "source": "faolex"}, {"name": "Règlement fixant des conditions à l’octroi de soutiens financiers à la production porcine vaudoise (RSFPV)", "year": "2018", "type": "Regulation", "sector": "Livestock", "sub": "Vaud", "url": "http://www.fao.org/faolex/results/details/en/c/LEX-FAOC192992", "source": "faolex"}, {"name": "Arrêté relatif au plan d'action cantonal en cas de concentrations excessives d'ozone (AOZONE)", "year": "2017", "type": "Regulation", "sector": "Environment", "sub": "Vaud", "url": "http://www.fao.org/faolex/results/details/en/c/LEX-FAOC192994", "source": "faolex"}, {"name": "Arrêté relatif au plan d'action cantonal en cas de concentrations excessives de poussières fines (PM-10) (ACEP)", "year": "2017", "type": "Regulation", "sector": "Environment", "sub": "Vaud", "url": "http://www.fao.org/faolex/results/details/en/c/LEX-FAOC192995", "source": "faolex"}, {"name": "Règlement sur le blocage – financement des vins vaudois (RBlocVins)", "year": "2016", "type": "Regulation", "sector": "Food and nutrition", "sub": "Vaud", "url": "http://www.fao.org/faolex/results/details/en/c/LEX-FAOC192993", "source": "faolex"}, {"name": "Loi d’application de la législation fédérale sur la protection des animaux (LVLPA)", "year": "2015", "type": "Legislation", "sector": "Livestock; Wild species and ecosystems", "sub": "Vaud", "url": "http://www.fao.org/faolex/results/details/en/c/LEX-FAOC192999", "source": "faolex"}, {"name": "Règlement d’application de l’Accord entre le Conseil fédéral suisse et le Gouvernement de la République française concernant la pêche dans le lac Léman (RA-Pêche-L)", "year": "2015", "type": "Regulation", "sector": "Fisheries and aquaculture", "sub": "Vaud", "url": "http://www.fao.org/faolex/results/details/en/c/LEX-FAOC193000", "source": "faolex"}, {"name": "Règlement d'exécution du concordat sur la pêche dans le lac de Morat en 2016, 2017 et 2018 (RC-Pêche-Morat)", "year": "2015", "type": "Regulation", "sector": "Fisheries and aquaculture", "sub": "Vaud", "url": "http://www.fao.org/faolex/results/details/en/c/LEX-FAOC193001", "source": "faolex"}, {"name": "Règlement d'exécution du concordat sur la pêche dans le lac de Neuchâtel en 2016, 2017 et 2018 (RC-Pêche-NE)", "year": "2015", "type": "Regulation", "sector": "Fisheries and aquaculture", "sub": "Vaud", "url": "http://www.fao.org/faolex/results/details/en/c/LEX-FAOC193002", "source": "faolex"}, {"name": "Directives sur l'exercice de la pêche dans les lacs de Joux, Brenet et Ter.", "year": "2014", "type": "Miscellaneous", "sector": "Fisheries and aquaculture", "sub": "Vaud", "url": "http://www.fao.org/faolex/results/details/en/c/LEX-FAOC147398", "source": "faolex"}, {"name": "Arrêté relatif aux contributions allouées pour les années 2014 à 2017 aux exploitants agricoles qui estivent leur bétail sur France (pacage franco-suisse) (A. Pacage).", "year": "2014", "type": "Regulation", "sector": "Agricultural and rural development", "sub": "Vaud", "url": "http://www.fao.org/faolex/results/details/en/c/LEX-FAOC152597", "source": "faolex"}, {"name": "Règlement modifiant le Règlement du 15 décembre 2010 sur le crédit agricole.", "year": "2014", "type": "Regulation", "sector": "Agricultural and rural development", "sub": "Vaud", "url": "http://www.fao.org/faolex/results/details/en/c/LEX-FAOC170358", "source": "faolex"}, {"name": "Règlement modifiant le Règlement du 15 décembre 2010 sur la promotion de l'économie agricole.", "year": "2013", "type": "Regulation", "sector": "Agricultural and rural development", "sub": "Vaud", "url": "http://www.fao.org/faolex/results/details/en/c/LEX-FAOC170357", "source": "faolex"}, {"name": "Règlement d'application de la loi forestière du 8 mai 2012 (RLVLFo)", "year": "2013", "type": "Regulation", "sector": "Forestry", "sub": "Vaud", "url": "http://www.fao.org/faolex/results/details/en/c/LEX-FAOC192998", "source": "faolex"}, {"name": "Règlement sur l'exercice de la pêche dans le lac de Morat en 2013, 2014 et 2015 (Rpêche - Morat).", "year": "2012", "type": "Regulation", "sector": "Fisheries and aquaculture", "sub": "Vaud", "url": "http://www.fao.org/faolex/results/details/en/c/LEX-FAOC147390", "source": "faolex"}, {"name": "Loi sur la géoinformation (LGéo-VD).", "year": "2012", "type": "Legislation", "sector": "Land and soil", "sub": "Vaud", "url": "http://www.fao.org/faolex/results/details/en/c/LEX-FAOC152562", "source": "faolex"}, {"name": "Règlement d'application de la loi du 8 mai 2012 sur la géoinformation (RLGéo-VD).", "year": "2012", "type": "Regulation", "sector": "Land and soil", "sub": "Vaud", "url": "http://www.fao.org/faolex/results/details/en/c/LEX-FAOC152563", "source": "faolex"}, {"name": "Loi forestière (LVLFO)", "year": "2012", "type": "Legislation", "sector": "Forestry", "sub": "Vaud", "url": "http://www.fao.org/faolex/results/details/en/c/LEX-FAOC192997", "source": "faolex"}, {"name": "Règlement sur l'utilisation des pompes à chaleur (RPCL).", "year": "2011", "type": "Regulation", "sector": "Environment", "sub": "Vaud", "url": "http://www.fao.org/faolex/results/details/en/c/LEX-FAOC152603", "source": "faolex"}, {"name": "Loi sur l'agriculture vaudoise (LVLAgr).", "year": "2010", "type": "Legislation", "sector": "Agricultural and rural development", "sub": "Vaud", "url": "http://www.fao.org/faolex/results/details/en/c/LEX-FAOC102377", "source": "faolex"}, {"name": "Règlement d'application de la loi sur l'agriculture vaudoise (RLVLAgr).", "year": "2010", "type": "Regulation", "sector": "Agricultural and rural development", "sub": "Vaud", "url": "http://www.fao.org/faolex/results/details/en/c/LEX-FAOC102378", "source": "faolex"}, {"name": "Règlement sur la promotion de l'économie agricole (RPEAgr).", "year": "2010", "type": "Regulation", "sector": "Agricultural and rural development", "sub": "Vaud", "url": "http://www.fao.org/faolex/results/details/en/c/LEX-FAOC102380", "source": "faolex"}, {"name": "Règlement sur l'agroécologie (RAgrEco).", "year": "2010", "type": "Regulation", "sector": "Agricultural and rural development", "sub": "Vaud", "url": "http://www.fao.org/faolex/results/details/en/c/LEX-FAOC102381", "source": "faolex"}, {"name": "Règlement sur le crédit agricole (RCAgr).", "year": "2010", "type": "Regulation", "sector": "Agricultural and rural development", "sub": "Vaud", "url": "http://www.fao.org/faolex/results/details/en/c/LEX-FAOC102431", "source": "faolex"}, {"name": "Règlement sur la protection des végétaux (RPV)", "year": "2010", "type": "Regulation", "sector": "Cultivated plants", "sub": "Vaud", "url": "http://www.fao.org/faolex/results/details/en/c/LEX-FAOC102434", "source": "faolex"}, {"name": "Loi d'application de l'ordonnance fédérale sur l'aide au Service consultatif et sanitaire en matière d'élevage de petits ruminants (LVOSSPR).", "year": "2010", "type": "Legislation", "sector": "Livestock", "sub": "Vaud", "url": "http://www.fao.org/faolex/results/details/en/c/LEX-FAOC102484", "source": "faolex"}, {"name": "Décret portant adoption de la première adaptation du Plan directeur cantonal (DPDCn1).", "year": "2010", "type": "Regulation", "sector": "Land and soil", "sub": "Vaud", "url": "http://www.fao.org/faolex/results/details/en/c/LEX-FAOC155463", "source": "faolex"}, {"name": "Règlement sur les vins vaudois (RVV).", "year": "2009", "type": "Regulation", "sector": "Cultivated plants", "sub": "Vaud", "url": "http://www.fao.org/faolex/results/details/en/c/LEX-FAOC102433", "source": "faolex"}, {"name": "Règlement d’exécution du concordat sur la pêche dans le lac de Morat (RC - Pêche - Morat).", "year": "2009", "type": "Regulation", "sector": "Fisheries and aquaculture", "sub": "Vaud", "url": "http://www.fao.org/faolex/results/details/en/c/LEX-FAOC147391", "source": "faolex"}, {"name": "Règlement d’exécution du concordat sur la pêche dans le lac de Neuchâtel (RC – Pêche – NE).", "year": "2009", "type": "Regulation", "sector": "Fisheries and aquaculture", "sub": "Vaud", "url": "http://www.fao.org/faolex/results/details/en/c/LEX-FAOC147397", "source": "faolex"}, {"name": "Loi sur le secteur électrique (LSecEl).", "year": "2009", "type": "Legislation", "sector": "Energy", "sub": "Vaud", "url": "http://www.fao.org/faolex/results/details/en/c/LEX-FAOC152594", "source": "faolex"}, {"name": "Règlement sur l’entretien des installations particulières d’épuration des eaux usées ménagères et des installations de prétraitement industrielles (RIEEU).", "year": "2009", "type": "Regulation", "sector": "Water", "sub": "Vaud", "url": "http://www.fao.org/faolex/results/details/en/c/LEX-FAOC152605", "source": "faolex"}, {"name": "Règlement sur l'indemnité communale liée à l'usage du sol pour la distribution d'électricité (Ri-DFEl).", "year": "2009", "type": "Regulation", "sector": "Energy", "sub": "Vaud", "url": "http://www.fao.org/faolex/results/details/en/c/LEX-FAOC157442", "source": "faolex"}, {"name": "Loi d'application sur les parcs d'importance nationale (LVOParcs).", "year": "2008", "type": "Legislation", "sector": "Wild species and ecosystems", "sub": "Vaud", "url": "http://www.fao.org/faolex/results/details/en/c/LEX-FAOC152564", "source": "faolex"}, {"name": "Règlement d'application de la loi du 5 septembre 2006 sur la gestion des déchets (RLGD).", "year": "2008", "type": "Regulation", "sector": "Environment", "sub": "Vaud", "url": "http://www.fao.org/faolex/results/details/en/c/LEX-FAOC152601", "source": "faolex"}, {"name": "Règlement modifiant le règlement du 25 avril 1990 d'application de l'ordonnance fédérale relative à l'étude de l'impact sur l'environnement.", "year": "2008", "type": "Regulation", "sector": "Environment", "sub": "Vaud", "url": "http://www.fao.org/faolex/results/details/en/c/LEX-FAOC170405", "source": "faolex"}, {"name": "Règlement d'application de la loi du 29 novembre 1978 sur la pêche (RLPêche).", "year": "2007", "type": "Regulation", "sector": "Fisheries and aquaculture", "sub": "Vaud", "url": "http://www.fao.org/faolex/results/details/en/c/LEX-FAOC102518", "source": "faolex"}, {"name": "Règlement d'application de la loi fédérale du 15 décembre 2000 sur les produits chimiques (RVLChim).", "year": "2007", "type": "Regulation", "sector": "Environment", "sub": "Vaud", "url": "http://www.fao.org/faolex/results/details/en/c/LEX-FAOC152629", "source": "faolex"}, {"name": "Loi sur l'appui au développement économique (LADE).", "year": "2007", "type": "Legislation", "sector": "Agricultural and rural development", "sub": "Vaud", "url": "http://www.fao.org/faolex/results/details/en/c/LEX-FAOC157574", "source": "faolex"}, {"name": "Règlement d'application de la loi forestière du 19 juin 1996 (RLVLFo).", "year": "2006", "type": "Regulation", "sector": "Forestry", "sub": "Vaud", "url": "http://www.fao.org/faolex/results/details/en/c/LEX-FAOC065270", "source": "faolex"}, {"name": "Loi sur l'énergie (LVLEne).", "year": "2006", "type": "Legislation", "sector": "Energy", "sub": "Vaud", "url": "http://www.fao.org/faolex/results/details/en/c/LEX-FAOC068288", "source": "faolex"}, {"name": "Règlement sur la Commission cantonale de surveillance du secteur électrique (RCSecEi).", "year": "2006", "type": "Regulation", "sector": "Energy", "sub": "Vaud", "url": "http://www.fao.org/faolex/results/details/en/c/LEX-FAOC068289", "source": "faolex"}, {"name": "Règlement d'application de la loi du 16 mai 2006 sur l'énergie (RLVLEne).", "year": "2006", "type": "Regulation", "sector": "Energy", "sub": "Vaud", "url": "http://www.fao.org/faolex/results/details/en/c/LEX-FAOC068293", "source": "faolex"}, {"name": "Loi sur l'assainissement des sites pollués (LASP).", "year": "2006", "type": "Legislation", "sector": "Land and soil", "sub": "Vaud", "url": "http://www.fao.org/faolex/results/details/en/c/LEX-FAOC068304", "source": "faolex"}, {"name": "Règlement sur le Fonds pour l'énergie (RF-Ene).", "year": "2006", "type": "Regulation", "sector": "Energy", "sub": "Vaud", "url": "http://www.fao.org/faolex/results/details/en/c/LEX-FAOC068307", "source": "faolex"}, {"name": "Loi sur la gestion des déchets (LGD).", "year": "2006", "type": "Legislation", "sector": "Environment", "sub": "Vaud", "url": "http://www.fao.org/faolex/results/details/en/c/LEX-FAOC140628", "source": "faolex"}, {"name": "Règlement sur l'organisation et la coordination des secours en cas d'accident majeur ou de catastrophe (RORCA).", "year": "2006", "type": "Regulation", "sector": "Environment; Disaster risk management", "sub": "Vaud", "url": "http://www.fao.org/faolex/results/details/en/c/LEX-FAOC152606", "source": "faolex"}, {"name": "Arrêté fixant le taux de la subvention cantonale pour les installations de compostage des déchets et les centres de ramassage des déchets cyclables (ASIC).", "year": "2006", "type": "Regulation", "sector": "Environment", "sub": "Vaud", "url": "http://www.fao.org/faolex/results/details/en/c/LEX-FAOC157443", "source": "faolex"}, {"name": "Règlement sur les réserves de chasse et de protection de la faune du Canton de Vaud (Règlement sur les réserves de faune) (RRCh).", "year": "2005", "type": "Regulation", "sector": "Wild species and ecosystems", "sub": "Vaud", "url": "http://www.fao.org/faolex/results/details/en/c/LEX-FAOC061289", "source": "faolex"}, {"name": "Règlement concernant la protection de la flore (RPF).", "year": "2005", "type": "Regulation", "sector": "Wild species and ecosystems", "sub": "Vaud", "url": "http://www.fao.org/faolex/results/details/en/c/LEX-FAOC068280", "source": "faolex"}, {"name": "Arrêté sur la destruction des nids de chenilles processionnaires du pin (ADChP)", "year": "2005", "type": "Regulation", "sector": "Cultivated plants", "sub": "Vaud", "url": "http://www.fao.org/faolex/results/details/en/c/LEX-FAOC192996", "source": "faolex"}, {"name": "Règlement sur le commerce et le contrôle des champignons (RChamp).", "year": "2004", "type": "Regulation", "sector": "Food and nutrition", "sub": "Vaud", "url": "http://www.fao.org/faolex/results/details/en/c/LEX-FAOC061205", "source": "faolex"}, {"name": "Règlement d'exécution de la loi du 28 février 1989 sur la faune (RLFaune).", "year": "2004", "type": "Regulation", "sector": "Wild species and ecosystems", "sub": "Vaud", "url": "http://www.fao.org/faolex/results/details/en/c/LEX-FAOC061288", "source": "faolex"}, {"name": "Loi sur la protection de la population (LProP).", "year": "2004", "type": "Legislation", "sector": "Environment; Disaster risk management", "sub": "Vaud", "url": "http://www.fao.org/faolex/results/details/en/c/LEX-FAOC068285", "source": "faolex"}, {"name": "Concordat sur la pêche dans le lac de Morat (C-Pêche-Morat).", "year": "2003", "type": "Miscellaneous", "sector": "Fisheries and aquaculture", "sub": "Vaud; Fribourg", "url": "http://www.fao.org/faolex/results/details/en/c/LEX-FAOC061366", "source": "faolex"}, {"name": "Règlement d'exécution du concordat du 19 mai 2003 sur la pêche dans le lac de Neuchâtel (RC-Pêche-NE).", "year": "2003", "type": "Regulation", "sector": "Fisheries and aquaculture", "sub": "Vaud", "url": "http://www.fao.org/faolex/results/details/en/c/LEX-FAOC061368", "source": "faolex"}, {"name": "Concordat sur la pêche dans le lac de Neuchâtel (C-Pêche-NE).", "year": "2003", "type": "Miscellaneous", "sector": "Fisheries and aquaculture", "sub": "Vaud; Fribourg; Neuchâtel", "url": "http://www.fao.org/faolex/results/details/en/c/LEX-FAOC065276", "source": "faolex"}, {"name": "Règlement d'exécution du concordat du 19 mai 2003 sur la pêche dans le lac de Morat (RC-Pêche-Morat).", "year": "2003", "type": "Regulation", "sector": "Fisheries and aquaculture", "sub": "Vaud", "url": "http://www.fao.org/faolex/results/details/en/c/LEX-FAOC065277", "source": "faolex"}, {"name": "Règlement sur l'exercice de la pêche dans le lac de Morat (RPêche-Morat).", "year": "2003", "type": "Regulation", "sector": "Fisheries and aquaculture", "sub": "Vaud", "url": "http://www.fao.org/faolex/results/details/en/c/LEX-FAOC065279", "source": "faolex"}, {"name": "Arrêté concernant la lutte contre les maladies du bois de la vigne et leur prophylaxie (ALMV).", "year": "2002", "type": "Regulation", "sector": "Cultivated plants", "sub": "Vaud", "url": "http://www.fao.org/faolex/results/details/en/c/LEX-FAOC061212", "source": "faolex"}, {"name": "Règlement sur le contrôle obligatoire des installations de chauffage à combustion (RCOCC).", "year": "2001", "type": "Regulation", "sector": "Environment", "sub": "Vaud", "url": "http://www.fao.org/faolex/results/details/en/c/LEX-FAOC152633", "source": "faolex"}, {"name": "Règlement fixant les conditions de l'estivage et de l'hivernage (RCEH).", "year": "2000", "type": "Regulation", "sector": "Livestock", "sub": "Vaud", "url": "http://www.fao.org/faolex/results/details/en/c/LEX-FAOC061215", "source": "faolex"}, {"name": "Règlement d'exécution du concordat intercantonal du 7 octobre 1999 sur la pêche dans le lac Léman (RC-Pêche-L).", "year": "2000", "type": "Regulation", "sector": "Fisheries and aquaculture", "sub": "Vaud", "url": "http://www.fao.org/faolex/results/details/en/c/LEX-FAOC065275", "source": "faolex"}, {"name": "Règlement d’application de l’ordonnance fédérale du 7 décembre 1998 sur la terminologie agricole et la reconnaissance des formes d’exploitation.", "year": "1999", "type": "Regulation", "sector": "Agricultural and rural development", "sub": "Vaud", "url": "http://www.fao.org/faolex/results/details/en/c/LEX-FAOC037835", "source": "faolex"}, {"name": "Règlement d’application de l’ordonnance fédérale du 7 décembre 1998 sur les paiements directs versés dans l’agriculture.", "year": "1999", "type": "Regulation", "sector": "Agricultural and rural development", "sub": "Vaud", "url": "http://www.fao.org/faolex/results/details/en/c/LEX-FAOC037837", "source": "faolex"}, {"name": "Règlement d’application de l’ordonnance fédérale du 7 décembre 1998 sur les contributions à la surface et à la transformation dans la culture des champs.", "year": "1999", "type": "Regulation", "sector": "Cultivated plants", "sub": "Vaud", "url": "http://www.fao.org/faolex/results/details/en/c/LEX-FAOC037838", "source": "faolex"}, {"name": "Règlement d’application de l’ordonnance fédérale du 7 décembre 1998 sur les contributions d’estivage dans l’agriculture.", "year": "1999", "type": "Regulation", "sector": "Livestock", "sub": "Vaud", "url": "http://www.fao.org/faolex/results/details/en/c/LEX-FAOC037840", "source": "faolex"}, {"name": "Règlement d’application de l’ordonnance fédérale du 7 décembre 1998 sur l’élevage.", "year": "1999", "type": "Regulation", "sector": "Livestock", "sub": "Vaud", "url": "http://www.fao.org/faolex/results/details/en/c/LEX-FAOC037841", "source": "faolex"}, {"name": "Arrêté concernant la lutte contre le feu bactérien et sa prophylaxie.", "year": "1999", "type": "Regulation", "sector": "Cultivated plants", "sub": "Vaud", "url": "http://www.fao.org/faolex/results/details/en/c/LEX-FAOC037843", "source": "faolex"}, {"name": "Concordat sur la pêche dans le lac Léman (C-Pêche-L).", "year": "1999", "type": "Miscellaneous", "sector": "Fisheries and aquaculture", "sub": "Vaud; Valais; Genève", "url": "http://www.fao.org/faolex/results/details/en/c/LEX-FAOC065274", "source": "faolex"}, {"name": "Règlement sur l’approbation des plans directeurs et des installations de distribution d’eau et sur l’approvisionnement en eau potable en temps de crise.", "year": "1998", "type": "Regulation", "sector": "Water", "sub": "Vaud", "url": "http://www.fao.org/faolex/results/details/en/c/LEX-FAOC037811", "source": "faolex"}, {"name": "Règlement sur la pêche dans les lacs de Joux, Brenet et Ter.", "year": "1998", "type": "Regulation", "sector": "Fisheries and aquaculture", "sub": "Vaud", "url": "http://www.fao.org/faolex/results/details/en/c/LEX-FAOC037818", "source": "faolex"}, {"name": "Concordat concernant la chasse sur le lac de Neuchâtel (C-Ch-NE).", "year": "1998", "type": "Miscellaneous", "sector": "Wild species and ecosystems", "sub": "Vaud; Neuchâtel; Fribourg", "url": "http://www.fao.org/faolex/results/details/en/c/LEX-FAOC061216", "source": "faolex"}, {"name": "Concordat concernant la chasse sur le lac de Morat (C-Ch-Morat).", "year": "1998", "type": "Miscellaneous", "sector": "Wild species and ecosystems", "sub": "Vaud; Fribourg", "url": "http://www.fao.org/faolex/results/details/en/c/LEX-FAOC061293", "source": "faolex"}, {"name": "Décret accordant un crédit destiné à soutenir la mise en conformité des installations de stockage des engrais de ferme exigée par la loi fédérale du 24 janvier 1991 sur la protection des eaux.", "year": "1997", "type": "Regulation", "sector": "Water", "sub": "Vaud", "url": "http://www.fao.org/faolex/results/details/en/c/LEX-FAOC037796", "source": "faolex"}, {"name": "Arrêté fixant des mesures particulières sur l'estivage en 1997.", "year": "1997", "type": "Regulation", "sector": "Livestock", "sub": "Vaud", "url": "http://www.fao.org/faolex/results/details/en/c/LEX-FAOC037798", "source": "faolex"}, {"name": "Règlement sur le séquestre et la mise en fourrière d’animaux.", "year": "1997", "type": "Regulation", "sector": "Livestock", "sub": "Vaud", "url": "http://www.fao.org/faolex/results/details/en/c/LEX-FAOC037801", "source": "faolex"}, {"name": "Arrêté concernant l’ouverture d’exploitations de pêche professionnelle dans le lac de Neuchâtel.", "year": "1997", "type": "Regulation", "sector": "Fisheries and aquaculture", "sub": "Vaud", "url": "http://www.fao.org/faolex/results/details/en/c/LEX-FAOC037805", "source": "faolex"}, {"name": "Règlement sur le commerce et le contrôle des champignons.", "year": "1997", "type": "Regulation", "sector": "Food and nutrition", "sub": "Vaud", "url": "http://www.fao.org/faolex/results/details/en/c/LEX-FAOC037806", "source": "faolex"}, {"name": "Règlement d’exécution du concordat du 21 mars 1980 sur la pêche dans le lac de Neuchâtel.", "year": "1997", "type": "Regulation", "sector": "Fisheries and aquaculture", "sub": "Vaud", "url": "http://www.fao.org/faolex/results/details/en/c/LEX-FAOC037808", "source": "faolex"}, {"name": "Règlement sur l’exercice de la pêche dans le lac de Neuchâtel.", "year": "1997", "type": "Regulation", "sector": "Fisheries and aquaculture", "sub": "Vaud", "url": "http://www.fao.org/faolex/results/details/en/c/LEX-FAOC037810", "source": "faolex"}, {"name": "Règlement pour la promotion des produits agricoles vaudois (RPPAV).", "year": "1997", "type": "Regulation", "sector": "Food and nutrition", "sub": "Vaud", "url": "http://www.fao.org/faolex/results/details/en/c/LEX-FAOC065252", "source": "faolex"}, {"name": "Directives concernant les mammifères et oiseaux sauvages tués accidentellement ou trouvés péris.", "year": "1997", "type": "Miscellaneous", "sector": "Wild species and ecosystems", "sub": "Vaud", "url": "http://www.fao.org/faolex/results/details/en/c/LEX-FAOC147399", "source": "faolex"}, {"name": "Règlement modifiant celui du 26 mars 1993 sur la qualité des vins vaudois.", "year": "1996", "type": "Regulation", "sector": "Food and nutrition", "sub": "Vaud", "url": "http://www.fao.org/faolex/results/details/en/c/LEX-FAOC011088", "source": "faolex"}, {"name": "Arrêté concernant l'ouverture d'exploitations de pêche professionnelle dans le lac Léman.", "year": "1996", "type": "Regulation", "sector": "Fisheries and aquaculture", "sub": "Vaud", "url": "http://www.fao.org/faolex/results/details/en/c/LEX-FAOC011090", "source": "faolex"}, {"name": "Décret accordant un crédit pour la protection des eaux contre la pollution.", "year": "1996", "type": "Regulation", "sector": "Water", "sub": "Vaud", "url": "http://www.fao.org/faolex/results/details/en/c/LEX-FAOC011091", "source": "faolex"}, {"name": "Loi modifiant celle du 30 novembre 1964 sur la distribution de l'eau.", "year": "1996", "type": "Legislation", "sector": "Food and nutrition; Water", "sub": "Vaud", "url": "http://www.fao.org/faolex/results/details/en/c/LEX-FAOC011092", "source": "faolex"}, {"name": "Arrêté concernant la pêche à la gambe dans le lac de Morat en 1997.", "year": "1996", "type": "Regulation", "sector": "Fisheries and aquaculture", "sub": "Vaud", "url": "http://www.fao.org/faolex/results/details/en/c/LEX-FAOC011093", "source": "faolex"}, {"name": "Arrêté concernant la pêche à la gambe dans le lac de Neuchâtel en 1997.", "year": "1996", "type": "Regulation", "sector": "Fisheries and aquaculture", "sub": "Vaud", "url": "http://www.fao.org/faolex/results/details/en/c/LEX-FAOC011094", "source": "faolex"}, {"name": "Règlement modifiant celui du 11 juin 1993 d'exécution de la loi du 28 février 1989 sur la faune.", "year": "1996", "type": "Regulation", "sector": "Wild species and ecosystems", "sub": "Vaud", "url": "http://www.fao.org/faolex/results/details/en/c/LEX-FAOC011095", "source": "faolex"}, {"name": "Règlement modifiant celui du 2 décembre 1987 d'exécution du concordat du 21 mars 1980 sur la pêche dans le lac de Neuchâtel.", "year": "1996", "type": "Regulation", "sector": "Fisheries and aquaculture", "sub": "Vaud", "url": "http://www.fao.org/faolex/results/details/en/c/LEX-FAOC011096", "source": "faolex"}, {"name": "Arrêté modifiant le règlement du 17 décembre 1993 d'exécution du concordat du 14 décembre 1979 sur la pêche dans le lac de Morat.", "year": "1996", "type": "Regulation", "sector": "Fisheries and aquaculture", "sub": "Vaud", "url": "http://www.fao.org/faolex/results/details/en/c/LEX-FAOC011097", "source": "faolex"}, {"name": "Arrêté concernant l'utilisation du carrelet dans le lac de Morat.", "year": "1996", "type": "Regulation", "sector": "Fisheries and aquaculture", "sub": "Vaud", "url": "http://www.fao.org/faolex/results/details/en/c/LEX-FAOC011139", "source": "faolex"}, {"name": "Loi modifiant celle du 25 mai 1970 d'application de la législation fédérale sur les épizooties.", "year": "1996", "type": "Legislation", "sector": "Livestock", "sub": "Vaud", "url": "http://www.fao.org/faolex/results/details/en/c/LEX-FAOC011140", "source": "faolex"}, {"name": "Règlement modifiant celui du 16 février 1979 d'application de la loi du 29 novembre 1978 sur la pêche.", "year": "1996", "type": "Regulation", "sector": "Fisheries and aquaculture", "sub": "Vaud", "url": "http://www.fao.org/faolex/results/details/en/c/LEX-FAOC011141", "source": "faolex"}, {"name": "Loi modifiant celle du 10 décembre 1969 sur la protection de la nature, des monuments et des sites.", "year": "1996", "type": "Legislation", "sector": "Wild species and ecosystems", "sub": "Vaud", "url": "http://www.fao.org/faolex/results/details/en/c/LEX-FAOC011142", "source": "faolex"}, {"name": "Règlement modifiant celui du 22 mars 1989 d'application de la loi du 10 décembre 1969 sur la protection de la nature, des monuments et des sites.", "year": "1996", "type": "Regulation", "sector": "Wild species and ecosystems", "sub": "Vaud", "url": "http://www.fao.org/faolex/results/details/en/c/LEX-FAOC011143", "source": "faolex"}, {"name": "Loi forestière.", "year": "1996", "type": "Legislation", "sector": "Forestry", "sub": "Vaud", "url": "http://www.fao.org/faolex/results/details/en/c/LEX-FAOC054160", "source": "faolex"}, {"name": "Règlement concernant le service d'inspection et de consultation en matière d'économie laitière (RSICEL).", "year": "1996", "type": "Regulation", "sector": "Food and nutrition", "sub": "Vaud", "url": "http://www.fao.org/faolex/results/details/en/c/LEX-FAOC061286", "source": "faolex"}, {"name": "Arrêté concernant la pêche de la perche dans le lac Léman.", "year": "1995", "type": "Regulation", "sector": "Fisheries and aquaculture", "sub": "Vaud", "url": "http://www.fao.org/faolex/results/details/en/c/LEX-FAOC009510", "source": "faolex"}, {"name": "Arrêté fixant des mesures particulières sur l'estivage en 1995.", "year": "1995", "type": "Regulation", "sector": "Livestock", "sub": "Vaud", "url": "http://www.fao.org/faolex/results/details/en/c/LEX-FAOC009512", "source": "faolex"}, {"name": "Règlement modifiant celui du 16 juillet 1993 sur la limitation de la production et le contrôle officiel de la vendange.", "year": "1995", "type": "Regulation", "sector": "Cultivated plants", "sub": "Vaud", "url": "http://www.fao.org/faolex/results/details/en/c/LEX-FAOC011078", "source": "faolex"}, {"name": "Arrêté concernant la pêche à la gambe dans le lac de Morat en 1995.", "year": "1995", "type": "Regulation", "sector": "Fisheries and aquaculture", "sub": "Vaud", "url": "http://www.fao.org/faolex/results/details/en/c/LEX-FAOC011079", "source": "faolex"}, {"name": "Arrêté concernant la pêche à la gambe dans le lac de Neuchâtel en 1995.", "year": "1995", "type": "Regulation", "sector": "Fisheries and aquaculture", "sub": "Vaud", "url": "http://www.fao.org/faolex/results/details/en/c/LEX-FAOC011080", "source": "faolex"}, {"name": "Loi modifiant celle du 10 décembre 1969 sur la protection de la nature, des monuments et des sites.", "year": "1995", "type": "Legislation", "sector": "Wild species and ecosystems", "sub": "Vaud", "url": "http://www.fao.org/faolex/results/details/en/c/LEX-FAOC011081", "source": "faolex"}, {"name": "Règlement d'application de la loi du 13 septembre 1993 sur les contributions pour des prestations de caractère écologique dans l'agriculture.", "year": "1995", "type": "Regulation", "sector": "Agricultural and rural development", "sub": "Vaud", "url": "http://www.fao.org/faolex/results/details/en/c/LEX-FAOC011082", "source": "faolex"}, {"name": "Règlement sur les abattoirs et les contrôles en relation avec l'abattage.", "year": "1995", "type": "Regulation", "sector": "Food and nutrition", "sub": "Vaud", "url": "http://www.fao.org/faolex/results/details/en/c/LEX-FAOC011083", "source": "faolex"}, {"name": "Règlement d'exécution du concordat inter cantonal du 4 juin 1984 sur la pêche dans le lac Léman.", "year": "1995", "type": "Regulation", "sector": "Fisheries and aquaculture", "sub": "Vaud", "url": "http://www.fao.org/faolex/results/details/en/c/LEX-FAOC011084", "source": "faolex"}, {"name": "Règlement sur les appellations d'origine contrôlées des vins vaudois.", "year": "1995", "type": "Regulation", "sector": "Food and nutrition", "sub": "Vaud", "url": "http://www.fao.org/faolex/results/details/en/c/LEX-FAOC011085", "source": "faolex"}, {"name": "Règlement modifiant celui du 2 décembre 1987 d'exécution du concordat du 21 mars 1980 sur la pêche dans le lac de Neuchâtel.", "year": "1995", "type": "Regulation", "sector": "Fisheries and aquaculture", "sub": "Vaud", "url": "http://www.fao.org/faolex/results/details/en/c/LEX-FAOC011086", "source": "faolex"}, {"name": "Loi relative à la promotion de l'économie agricole vaudoise.", "year": "1995", "type": "Legislation", "sector": "Agricultural and rural development", "sub": "Vaud", "url": "http://www.fao.org/faolex/results/details/en/c/LEX-FAOC011087", "source": "faolex"}, {"name": "Loi d'exécution de la législation fédérale sur la protection civile (LVLPCi).", "year": "1995", "type": "Legislation", "sector": "Environment; Disaster risk management", "sub": "Vaud", "url": "http://www.fao.org/faolex/results/details/en/c/LEX-FAOC157444", "source": "faolex"}, {"name": "Modification du règlement du 7 juin 1985 sur la pêche dans les lacs de Joux, Brenet et Ter.", "year": "1994", "type": "Regulation", "sector": "Fisheries and aquaculture", "sub": "Vaud", "url": "http://www.fao.org/faolex/results/details/en/c/LEX-FAOC009497", "source": "faolex"}, {"name": "Règlement sur la protection des plantes et relatif aux permis pour l'utilisation des produits de traitement des plants.", "year": "1994", "type": "Regulation", "sector": "Cultivated plants", "sub": "Vaud", "url": "http://www.fao.org/faolex/results/details/en/c/LEX-FAOC009499", "source": "faolex"}, {"name": "Arrêté sur les arrondissements d'inspection du bétail.", "year": "1994", "type": "Regulation", "sector": "Livestock", "sub": "Vaud", "url": "http://www.fao.org/faolex/results/details/en/c/LEX-FAOC009503", "source": "faolex"}, {"name": "Arrêté modifiant le règlement du 17 décembre 1993 d'exécution du concordat du 14 décembre 1979 sur la pêche dans le lac de Morat.", "year": "1994", "type": "Regulation", "sector": "Fisheries and aquaculture", "sub": "Vaud", "url": "http://www.fao.org/faolex/results/details/en/c/LEX-FAOC009504", "source": "faolex"}, {"name": "Arrêté relatif au placement du bétail.", "year": "1994", "type": "Regulation", "sector": "Livestock", "sub": "Vaud", "url": "http://www.fao.org/faolex/results/details/en/c/LEX-FAOC009505", "source": "faolex"}, {"name": "Loi relative à l'exécution de la loi fédérale du 1992 sur les denrées alimentaires et les objets usuels.", "year": "1994", "type": "Legislation", "sector": "Food and nutrition", "sub": "Vaud", "url": "http://www.fao.org/faolex/results/details/en/c/LEX-FAOC009506", "source": "faolex"}, {"name": "Modification du règlement du 16 juillet 1993 sur la limitation de la production et le contrôle officiele de la vendange.", "year": "1994", "type": "Regulation", "sector": "Food and nutrition", "sub": "Vaud", "url": "http://www.fao.org/faolex/results/details/en/c/LEX-FAOC009638", "source": "faolex"}, {"name": "Règlement sur la vidange et l'entretien des installations particulières d'épuration d'eaux usées ménagères et résiduaires industrielles.", "year": "1994", "type": "Regulation", "sector": "Water", "sub": "Vaud", "url": "http://www.fao.org/faolex/results/details/en/c/LEX-FAOC054159", "source": "faolex"}, {"name": "Modification de la loi du 29 novembre 1978 sur la pêche.", "year": "1993", "type": "Regulation", "sector": "Fisheries and aquaculture", "sub": "Vaud", "url": "http://www.fao.org/faolex/results/details/en/c/LEX-FAOC009485", "source": "faolex"}, {"name": "Modification du règlement du 16 février 1979 d'application de la loi du 29 novembre 1978 sur la pêche.", "year": "1993", "type": "Regulation", "sector": "Fisheries and aquaculture", "sub": "Vaud", "url": "http://www.fao.org/faolex/results/details/en/c/LEX-FAOC009488", "source": "faolex"}, {"name": "Modification du règlement du 16 mai 1980 d'application de la loi du 5 juin 1979 forestière.", "year": "1993", "type": "Regulation", "sector": "Forestry", "sub": "Vaud", "url": "http://www.fao.org/faolex/results/details/en/c/LEX-FAOC009493", "source": "faolex"}, {"name": "Modification du règlement du 2 décembre 1987 d'exécution du concordat du 21 mars 1980 sur la pêche dans le lac de Neuchâtel.", "year": "1993", "type": "Regulation", "sector": "Fisheries and aquaculture", "sub": "Vaud", "url": "http://www.fao.org/faolex/results/details/en/c/LEX-FAOC009495", "source": "faolex"}, {"name": "Règlement d’application de la loi du 13 décembre 1989 sur la gestion des déchets.", "year": "1993", "type": "Regulation", "sector": "Environment", "sub": "Vaud", "url": "http://www.fao.org/faolex/results/details/en/c/LEX-FAOC054062", "source": "faolex"}, {"name": "Règlement d'exécution de la loi du 28 février 1989 sur la faune.", "year": "1993", "type": "Regulation", "sector": "Wild species and ecosystems", "sub": "Vaud", "url": "http://www.fao.org/faolex/results/details/en/c/LEX-FAOC054179", "source": "faolex"}, {"name": "Loi sur les contributions pour des prestations de caractère écologique dans l'agriculture (LECOP).", "year": "1993", "type": "Legislation", "sector": "Agricultural and rural development", "sub": "Vaud", "url": "http://www.fao.org/faolex/results/details/en/c/LEX-FAOC060764", "source": "faolex"}, {"name": "Règlement sur les mesures financières visant à favoriser une utilisation rationnelle de l'énergie (RURE).", "year": "1993", "type": "Regulation", "sector": "Energy", "sub": "Vaud", "url": "http://www.fao.org/faolex/results/details/en/c/LEX-FAOC065222", "source": "faolex"}, {"name": "Loi d'application de la loi fédérale du 4 octobre 1991 sur le droit foncier rural (LVLDFR).", "year": "1993", "type": "Legislation", "sector": "Land and soil", "sub": "Vaud", "url": "http://www.fao.org/faolex/results/details/en/c/LEX-FAOC065265", "source": "faolex"}, {"name": "Règlement sur la limitation de la production et le contrôle officiel de la vendange (RLPV).", "year": "1993", "type": "Regulation", "sector": "Cultivated plants", "sub": "Vaud", "url": "http://www.fao.org/faolex/results/details/en/c/LEX-FAOC065268", "source": "faolex"}, {"name": "Règlement sur la qualité des vins vaudois (RQVV).", "year": "1993", "type": "Regulation", "sector": "Food and nutrition", "sub": "Vaud", "url": "http://www.fao.org/faolex/results/details/en/c/LEX-FAOC065269", "source": "faolex"}, {"name": "Modification du règlement du 16 novembre 1979 d'application de la loi du 17 septembre 1974 sur la protection des eaux contre la pollution.", "year": "1992", "type": "Regulation", "sector": "Water", "sub": "Vaud", "url": "http://www.fao.org/faolex/results/details/en/c/LEX-FAOC008767", "source": "faolex"}, {"name": "Modification du règlement du 16 février 1979 d'application de la loi du 29 novembre 1978 sur la pêche.", "year": "1992", "type": "Regulation", "sector": "Fisheries and aquaculture", "sub": "Vaud", "url": "http://www.fao.org/faolex/results/details/en/c/LEX-FAOC008768", "source": "faolex"}, {"name": "Modification du règlement du 2 juin 1982 sur la protection des animaux.", "year": "1992", "type": "Regulation", "sector": "Livestock", "sub": "Vaud", "url": "http://www.fao.org/faolex/results/details/en/c/LEX-FAOC008769", "source": "faolex"}, {"name": "Règlement relatif à l'orientation de la production végétale et à l'exploitation extensive.", "year": "1992", "type": "Regulation", "sector": "Cultivated plants", "sub": "Vaud", "url": "http://www.fao.org/faolex/results/details/en/c/LEX-FAOC008770", "source": "faolex"}, {"name": "Modification du règlement du 16 novembre 1979 d'application de la loi du 17 septembre 1974 sur la protection des eaux contre la pollution.", "year": "1992", "type": "Regulation", "sector": "Water", "sub": "Vaud", "url": "http://www.fao.org/faolex/results/details/en/c/LEX-FAOC008771", "source": "faolex"}, {"name": "Arrêté relatif au soutien de la lutte contre l'arthrite-encéphalite caprine.", "year": "1992", "type": "Regulation", "sector": "Livestock", "sub": "Vaud", "url": "http://www.fao.org/faolex/results/details/en/c/LEX-FAOC008772", "source": "faolex"}, {"name": "Règlement sur les réserves de chasse et de protection de la faune du Canton de Vaud (Réserves de faune).", "year": "1992", "type": "Regulation", "sector": "Wild species and ecosystems", "sub": "Vaud", "url": "http://www.fao.org/faolex/results/details/en/c/LEX-FAOC054180", "source": "faolex"}, {"name": "Modification du règlement du 27 octobre 1980 d'exécution du concordat du 14 décembre 1979 sur la pêche dans le lac de Morat.", "year": "1991", "type": "Regulation", "sector": "Fisheries and aquaculture", "sub": "Vaud", "url": "http://www.fao.org/faolex/results/details/en/c/LEX-FAOC008763", "source": "faolex"}, {"name": "Modification du règlement du 16 février 1979 d'application de la loi du 29 novembre 1978 sur la pêche.", "year": "1991", "type": "Regulation", "sector": "Fisheries and aquaculture", "sub": "Vaud", "url": "http://www.fao.org/faolex/results/details/en/c/LEX-FAOC008764", "source": "faolex"}, {"name": "Modification de la loi du 21 novembre 1973 sur la viticulture.", "year": "1991", "type": "Regulation", "sector": "Cultivated plants", "sub": "Vaud", "url": "http://www.fao.org/faolex/results/details/en/c/LEX-FAOC008765", "source": "faolex"}, {"name": "Avenant au concordat du 14 décmbre 1979 sur la pêche dans le lac de Morat.", "year": "1991", "type": "Regulation", "sector": "Fisheries and aquaculture", "sub": "Vaud", "url": "http://www.fao.org/faolex/results/details/en/c/LEX-FAOC008766", "source": "faolex"}, {"name": "Règlement sur les hydrocarbures (RLHydr).", "year": "1991", "type": "Regulation", "sector": "Mineral resources", "sub": "Vaud", "url": "http://www.fao.org/faolex/results/details/en/c/LEX-FAOC102374", "source": "faolex"}, {"name": "Règlement d'application de l'ordonnance fédérale relative à l'étude de l'impact sur l'environnement (RVOEIE).", "year": "1990", "type": "Regulation", "sector": "Environment", "sub": "Vaud", "url": "http://www.fao.org/faolex/results/details/en/c/LEX-FAOC054060", "source": "faolex"}, {"name": "Arrêté relatif à l'encouragement de la production animale en montagne (APAM).", "year": "1990", "type": "Regulation", "sector": "Livestock", "sub": "Vaud", "url": "http://www.fao.org/faolex/results/details/en/c/LEX-FAOC061206", "source": "faolex"}, {"name": "Règlement d'application de la loi du 27 mai 1970 sur la prévention des incendies et des dangers résultant des éléments naturels (RLPIEN).", "year": "1990", "type": "Regulation", "sector": "Environment", "sub": "Vaud", "url": "http://www.fao.org/faolex/results/details/en/c/LEX-FAOC102559", "source": "faolex"}, {"name": "Règlement d'application de la loi fédérale du 7 octobre 1983 sur la protection de l'environnement.", "year": "1989", "type": "Regulation", "sector": "Environment", "sub": "Vaud", "url": "http://www.fao.org/faolex/results/details/en/c/LEX-FAOC054058", "source": "faolex"}, {"name": "Loi sur la gestion des déchets.", "year": "1989", "type": "Legislation", "sector": "Environment", "sub": "Vaud", "url": "http://www.fao.org/faolex/results/details/en/c/LEX-FAOC054061", "source": "faolex"}, {"name": "Règlement d'application de la loi fédérale du 21 mars 1969 sur le commerce des toxiques (Loi sur les toxiques).", "year": "1989", "type": "Regulation", "sector": "Environment", "sub": "Vaud", "url": "http://www.fao.org/faolex/results/details/en/c/LEX-FAOC054070", "source": "faolex"}, {"name": "Loi sur la faune.", "year": "1989", "type": "Legislation", "sector": "Wild species and ecosystems", "sub": "Vaud", "url": "http://www.fao.org/faolex/results/details/en/c/LEX-FAOC054164", "source": "faolex"}, {"name": "Règlement d'application de la loi du 10 décembre 1969 sur la protection de la nature, des monuments et des sites (RPNMS).", "year": "1989", "type": "Regulation", "sector": "Wild species and ecosystems", "sub": "Vaud", "url": "http://www.fao.org/faolex/results/details/en/c/LEX-FAOC054182", "source": "faolex"}, {"name": "Règlement d'application de la loi du 29 novembre 1961 sur les améliorations foncières (RLAF).", "year": "1988", "type": "Regulation", "sector": "Land and soil", "sub": "Vaud", "url": "http://www.fao.org/faolex/results/details/en/c/LEX-FAOC102426", "source": "faolex"}, {"name": "Règlement fixant les mesures financières en faveur des améliorations foncières (RMFAF).", "year": "1988", "type": "Regulation", "sector": "Land and soil", "sub": "Vaud", "url": "http://www.fao.org/faolex/results/details/en/c/LEX-FAOC152638", "source": "faolex"}, {"name": "Arrêté désignant l'autorité chargée d'appliquer l'article 15, deuxième alinéa, de la loi fédérale sur l'expropriation (AVLEx).", "year": "1987", "type": "Regulation", "sector": "Land and soil", "sub": "Vaud", "url": "http://www.fao.org/faolex/results/details/en/c/LEX-FAOC152607", "source": "faolex"}, {"name": "Code rural et foncier", "year": "1987", "type": "Legislation", "sector": "Agricultural and rural development; Land and soil", "sub": "Vaud", "url": "http://www.fao.org/faolex/results/details/en/c/LEX-FAOC199758", "source": "faolex"}, {"name": "Règlement d'application de la loi du 4 décembre 1985 sur l'aménagement du territoire et les constructions (RLATC).", "year": "1986", "type": "Regulation", "sector": "Land and soil", "sub": "Vaud", "url": "http://www.fao.org/faolex/results/details/en/c/LEX-FAOC065216", "source": "faolex"}, {"name": "Loi sur l'aménagement du territoire et les constructions (LATC).", "year": "1985", "type": "Legislation", "sector": "Land and soil", "sub": "Vaud", "url": "http://www.fao.org/faolex/results/details/en/c/LEX-FAOC060771", "source": "faolex"}, {"name": "Règlement sur les réserves de pêche, les parcours de pêche sans permis et les parcours intercantonaux du Canton de Vaud (RRPêche).", "year": "1984", "type": "Regulation", "sector": "Fisheries and aquaculture", "sub": "Vaud", "url": "http://www.fao.org/faolex/results/details/en/c/LEX-FAOC061294", "source": "faolex"}, {"name": "Loi d'application de la loi fédérale sur la responsabilité civile en matière nucléaire du 18 mars 1983 (LVLRCN).", "year": "1984", "type": "Legislation", "sector": "Environment", "sub": "Vaud", "url": "http://www.fao.org/faolex/results/details/en/c/LEX-FAOC068821", "source": "faolex"}, {"name": "Règlement sur l'utilisation des pompes à chaleur.", "year": "1982", "type": "Regulation", "sector": "Land and soil", "sub": "Vaud", "url": "http://www.fao.org/faolex/results/details/en/c/LEX-FAOC060772", "source": "faolex"}, {"name": "Règlement sur la protection des animaux (RPA).", "year": "1982", "type": "Regulation", "sector": "Livestock", "sub": "Vaud", "url": "http://www.fao.org/faolex/results/details/en/c/LEX-FAOC061290", "source": "faolex"}, {"name": "Arrêté limitant la navigation sur la Versoix et dans l'étang des Crénées pour la protection des intérêts piscicoles et de la faune (AVersoix).", "year": "1981", "type": "Regulation", "sector": "Fisheries and aquaculture", "sub": "Vaud", "url": "http://www.fao.org/faolex/results/details/en/c/LEX-FAOC147389", "source": "faolex"}, {"name": "Décret sur la protection des eaux contre la pollution et modifiant l'article 59, alinéa 2, de la loi du 17 septembre 1974 (DPEP).", "year": "1981", "type": "Regulation", "sector": "Water", "sub": "Vaud", "url": "http://www.fao.org/faolex/results/details/en/c/LEX-FAOC152637", "source": "faolex"}, {"name": "Règlement d'application de la loi du du 29 novembre 1979 sur la pêche.", "year": "1979", "type": "Regulation", "sector": "Fisheries and aquaculture", "sub": "Vaud", "url": "http://www.fao.org/faolex/results/details/en/c/LEX-FAOC065271", "source": "faolex"}, {"name": "Règlement d'application de la loi du 17 septembre 1974 sur la protection des eaux contre la pollution (RLPEP).", "year": "1979", "type": "Regulation", "sector": "Water", "sub": "Vaud", "url": "http://www.fao.org/faolex/results/details/en/c/LEX-FAOC152595", "source": "faolex"}, {"name": "Loi sur la pêche.", "year": "1978", "type": "Legislation", "sector": "Fisheries and aquaculture", "sub": "Vaud", "url": "http://www.fao.org/faolex/results/details/en/c/LEX-FAOC054161", "source": "faolex"}, {"name": "Concordat sur l'exercice et la surveillance de la chasse (C-Ch).", "year": "1978", "type": "Miscellaneous", "sector": "Wild species and ecosystems", "sub": "Vaud; Fribourg; Neuchâtel", "url": "http://www.fao.org/faolex/results/details/en/c/LEX-FAOC061291", "source": "faolex"}, {"name": "Règlement de la Commission consultative arboricole (RCCA).", "year": "1978", "type": "Regulation", "sector": "Cultivated plants", "sub": "Vaud", "url": "http://www.fao.org/faolex/results/details/en/c/LEX-FAOC065266", "source": "faolex"}, {"name": "Arrêté concernant la destruction des plantes nuisibles à l'agriculture (ADPNA).", "year": "1976", "type": "Regulation", "sector": "Cultivated plants", "sub": "Vaud", "url": "http://www.fao.org/faolex/results/details/en/c/LEX-FAOC061209", "source": "faolex"}, {"name": "Loi sur les mesures de compensation liées à la création de zones agricoles (LCZA).", "year": "1976", "type": "Legislation", "sector": "Land and soil", "sub": "Vaud", "url": "http://www.fao.org/faolex/results/details/en/c/LEX-FAOC065217", "source": "faolex"}, {"name": "Arrêté concernant la protection des escargots (APEsc).", "year": "1976", "type": "Regulation", "sector": "Wild species and ecosystems", "sub": "Vaud", "url": "http://www.fao.org/faolex/results/details/en/c/LEX-FAOC102517", "source": "faolex"}, {"name": "Règlement de la navigation sur le Léman (RNav).", "year": "1976", "type": "Regulation", "sector": "Water", "sub": "Vaud", "url": "http://www.fao.org/faolex/results/details/en/c/LEX-FAOC152632", "source": "faolex"}, {"name": "Loi sur la protection des eaux contre la pollution.", "year": "1974", "type": "Legislation", "sector": "Water", "sub": "Vaud", "url": "http://www.fao.org/faolex/results/details/en/c/LEX-FAOC054157", "source": "faolex"}, {"name": "Arrêté sur les silos-enveloppes.", "year": "1974", "type": "Regulation", "sector": "Water", "sub": "Vaud", "url": "http://www.fao.org/faolex/results/details/en/c/LEX-FAOC060769", "source": "faolex"}, {"name": "Loi sur l'expropriation (LE).", "year": "1974", "type": "Legislation", "sector": "Land and soil", "sub": "Vaud", "url": "http://www.fao.org/faolex/results/details/en/c/LEX-FAOC065218", "source": "faolex"}, {"name": "Arrêté sur l'accès aux surfaces gelées des lacs et cours d'eau dépendant du domaine public (ASGDP).", "year": "1974", "type": "Regulation", "sector": "Water", "sub": "Vaud", "url": "http://www.fao.org/faolex/results/details/en/c/LEX-FAOC152602", "source": "faolex"}, {"name": "Arrêté sur les mesures de protection des eaux à prendre lors de la construction et de l'exploitation de silos à fourrage.", "year": "1972", "type": "Regulation", "sector": "Water", "sub": "Vaud", "url": "http://www.fao.org/faolex/results/details/en/c/LEX-FAOC060770", "source": "faolex"}, {"name": "Loi d'application de la législation fédérale sur les épizooties (LVLFE).", "year": "1970", "type": "Legislation", "sector": "Livestock", "sub": "Vaud", "url": "http://www.fao.org/faolex/results/details/en/c/LEX-FAOC102490", "source": "faolex"}, {"name": "Règlement d'exécution de la loi d'application de la législation fédérale sur les épizooties (RLVLFE).", "year": "1970", "type": "Regulation", "sector": "Livestock", "sub": "Vaud", "url": "http://www.fao.org/faolex/results/details/en/c/LEX-FAOC102515", "source": "faolex"}, {"name": "Loi sur la prévention des incendies et des dangers résultant des éléments naturels (LPIEN).", "year": "1970", "type": "Legislation", "sector": "Environment; Disaster risk management", "sub": "Vaud", "url": "http://www.fao.org/faolex/results/details/en/c/LEX-FAOC102558", "source": "faolex"}, {"name": "Loi sur la protection de la nature, des monuments et des sites (LPNMS).", "year": "1969", "type": "Legislation", "sector": "Wild species and ecosystems", "sub": "Vaud", "url": "http://www.fao.org/faolex/results/details/en/c/LEX-FAOC054243", "source": "faolex"}, {"name": "Concordat sur l'exercice de la pêche (C-Pêche).", "year": "1968", "type": "Miscellaneous", "sector": "Fisheries and aquaculture", "sub": "Vaud; Neuchâtel; Fribourg", "url": "http://www.fao.org/faolex/results/details/en/c/LEX-FAOC061295", "source": "faolex"}, {"name": "Loi sur la distribution de l'eau (LDE).", "year": "1964", "type": "Legislation", "sector": "Food and nutrition; Water", "sub": "Vaud", "url": "http://www.fao.org/faolex/results/details/en/c/LEX-FAOC065215", "source": "faolex"}, {"name": "Loi sur l'arboriculture fruitière (LARF).", "year": "1964", "type": "Legislation", "sector": "Cultivated plants", "sub": "Vaud", "url": "http://www.fao.org/faolex/results/details/en/c/LEX-FAOC065267", "source": "faolex"}, {"name": "Règlement concernant l'insémination artificielle et les inséminateurs (RIAI).", "year": "1963", "type": "Regulation", "sector": "Livestock", "sub": "Vaud", "url": "http://www.fao.org/faolex/results/details/en/c/LEX-FAOC061213", "source": "faolex"}, {"name": "Loi sur les améliorations foncières (LAF).", "year": "1961", "type": "Legislation", "sector": "Land and soil", "sub": "Vaud", "url": "http://www.fao.org/faolex/results/details/en/c/LEX-FAOC061207", "source": "faolex"}, {"name": "Règlement sur la police des eaux dépendant du domaine public (RLPDP).", "year": "1958", "type": "Regulation", "sector": "Water", "sub": "Vaud", "url": "http://www.fao.org/faolex/results/details/en/c/LEX-FAOC157440", "source": "faolex"}, {"name": "Loi instituant un office central de la culture maraîchère (LOCCM).", "year": "1957", "type": "Legislation", "sector": "Cultivated plants", "sub": "Vaud", "url": "http://www.fao.org/faolex/results/details/en/c/LEX-FAOC061210", "source": "faolex"}, {"name": "Loi sur les hydrocarbures (LHydr).", "year": "1957", "type": "Legislation", "sector": "Mineral resources", "sub": "Vaud", "url": "http://www.fao.org/faolex/results/details/en/c/LEX-FAOC102370", "source": "faolex"}, {"name": "Loi sur la police des eaux dépendant du domaine public (LPDP).", "year": "1957", "type": "Legislation", "sector": "Water", "sub": "Vaud", "url": "http://www.fao.org/faolex/results/details/en/c/LEX-FAOC152541", "source": "faolex"}, {"name": "Règlement sur la commission cantonale de surveillance des entreprises électriques (RCs-EE).", "year": "1955", "type": "Regulation", "sector": "Energy", "sub": "Vaud", "url": "http://www.fao.org/faolex/results/details/en/c/LEX-FAOC065235", "source": "faolex"}, {"name": "Règlement d'application de la loi du 5 septembre 1944 sur l'utilisation des lacs et cours d'eau dépendant du domaine public et de la loi du 12 mai 1948 réglant l'occupation et l'exploitation des eaux souterraines dépendant du domaine public cantonal.", "year": "1953", "type": "Regulation", "sector": "Water", "sub": "Vaud", "url": "http://www.fao.org/faolex/results/details/en/c/LEX-FAOC054183", "source": "faolex"}, {"name": "Loi réglant l'occupation et l'exploitation des eaux souterraines dépendant du domaine public cantonal (LESDP).", "year": "1948", "type": "Legislation", "sector": "Water", "sub": "Vaud", "url": "http://www.fao.org/faolex/results/details/en/c/LEX-FAOC102680", "source": "faolex"}, {"name": "Loi sur l’utilisation des lacs et cours d’eau dépendant du domaine public.", "year": "1944", "type": "Legislation", "sector": "Water", "sub": "Vaud", "url": "http://www.fao.org/faolex/results/details/en/c/LEX-FAOC054069", "source": "faolex"}, {"name": "Arrêté abrogeant et remplaçant celui du 13 mars 1925 concernant la division du canton en arrondissements forestiers (ADCAF).", "year": "1926", "type": "Regulation", "sector": "Forestry", "sub": "Vaud", "url": "http://www.fao.org/faolex/results/details/en/c/LEX-FAOC061287", "source": "faolex"}, {"name": "Loi sur la procédure à suivre en matière de garantie dans le commerce du bétail (LGCB).", "year": "1911", "type": "Legislation", "sector": "Livestock", "sub": "Vaud", "url": "http://www.fao.org/faolex/results/details/en/c/LEX-FAOC102477", "source": "faolex"}, {"name": "Arrêté concernant la surveillance à exercer par l'Etat sur les mines et carrières (AMines).", "year": "1897", "type": "Regulation", "sector": "Mineral resources", "sub": "Vaud", "url": "http://www.fao.org/faolex/results/details/en/c/LEX-FAOC102557", "source": "faolex"}, {"name": "Loi sur les mines (LMines).", "year": "1891", "type": "Legislation", "sector": "Mineral resources", "sub": "Vaud", "url": "http://www.fao.org/faolex/results/details/en/c/LEX-FAOC102519", "source": "faolex"}, {"name": "Règlement sur les mines (RLMines).", "year": "1891", "type": "Regulation", "sector": "Mineral resources", "sub": "Vaud", "url": "http://www.fao.org/faolex/results/details/en/c/LEX-FAOC102556", "source": "faolex"}]