[{"name": "Ley de Cantabria 5/2022, de 15 de julio, de Ordenación del Territorio y Urbanismo de Cantabria.", "year": "2022", "type": "Legislation", "sector": "Land and soil", "sub": "Cantabria", "url": "http://www.fao.org/faolex/results/details/en/c/LEX-FAOC212007", "source": "faolex", "domain": "Agricultural and rural development; Environment; Land and soil", "jur": "Spain"}, {"name": "Resolución de 25 de marzo de 2020, por la que queda suspendida la caza y la pesca en aguas continentales en la Comunidad Autónoma de Cantabria durante la vigencia del Estado de Alarma.", "year": "2020", "type": "Regulation", "sector": "Fisheries and aquaculture", "sub": "Cantabria", "url": "http://www.fao.org/faolex/results/details/en/c/LEX-FAOC194549", "source": "faolex", "domain": "Fisheries and aquaculture; General", "jur": "Spain"}, {"name": "Ley Nº 6/2018 - Crea el Organismo Autónomo Servicio de Emergencias de Cantabria.", "year": "2019", "type": "Legislation", "sector": "Disaster risk management; General", "sub": "Cantabria", "url": "http://www.fao.org/faolex/results/details/en/c/LEX-FAOC187119", "source": "faolex", "domain": "Environment", "jur": "Spain"}, {"name": "Ley Nº 3/2018 - Ley de creación del Consejo de la Mujer.", "year": "2018", "type": "Legislation", "sector": "Gender", "sub": "Cantabria", "url": "http://www.fao.org/faolex/results/details/en/c/LEX-FAOC182359", "source": "faolex", "domain": "Agricultural and rural development", "jur": "Spain"}, {"name": "Ley Nº 5/2017 - Modifica la Ley Nº 2/2001, Ley de Ordenación Territorial y Régimen Urbanístico del Suelo de Cantabria.", "year": "2017", "type": "Legislation", "sector": "Land and soil", "sub": "Cantabria", "url": "http://www.fao.org/faolex/results/details/en/c/LEX-FAOC168594", "source": "faolex", "domain": "Land and soil", "jur": "Spain"}, {"name": "Ley Nº 3/2016 - Modifica la Ley Nº 2/2001, Ley de Ordenación Territorial y Régimen Urbanístico del Suelo de Cantabria.", "year": "2016", "type": "Legislation", "sector": "Land and soil", "sub": "Cantabria", "url": "http://www.fao.org/faolex/results/details/en/c/LEX-FAOC161024", "source": "faolex", "domain": "Land and soil", "jur": "Spain"}, {"name": "Ley Nº 6/2013 - Ley de cooperativas de Cantabria.", "year": "2013", "type": "Legislation", "sector": "Private sector and entrepreneurship", "sub": "Cantabria", "url": "http://www.fao.org/faolex/results/details/en/c/LEX-FAOC128754", "source": "faolex", "domain": "Agricultural and rural development", "jur": "Spain"}, {"name": "Ley Nº 7/2013 - Ley por la que se regula el aprovechamiento eólico en la Comunidad Autónoma de Cantabria.", "year": "2013", "type": "Legislation", "sector": "Energy", "sub": "Cantabria", "url": "http://www.fao.org/faolex/results/details/en/c/LEX-FAOC129230", "source": "faolex", "domain": "Energy", "jur": "Spain"}, {"name": "Ley Nº 8/2013 - Modifica la Ley Nº 2/2004, Ley del Plan de Ordenación del Litoral.", "year": "2013", "type": "Legislation", "sector": "Environment", "sub": "Cantabria", "url": "http://www.fao.org/faolex/results/details/en/c/LEX-FAOC129704", "source": "faolex", "domain": "Environment; Land and soil; Sea", "jur": "Spain"}, {"name": "Ley Nº 3/2012 - Modifica la Ley Nº 2/2001, Ley de Ordenación Territorial y Régimen Urbanístico del Suelo de Cantabria.", "year": "2012", "type": "Legislation", "sector": "Land and soil", "sub": "Cantabria", "url": "http://www.fao.org/faolex/results/details/en/c/LEX-FAOC114644", "source": "faolex", "domain": "Land and soil", "jur": "Spain"}, {"name": "Ley Nº 5/2012 - Ley de Reforma del Régimen Transitorio en materia de Ordenación del Territorio y Urbanismo.", "year": "2012", "type": "Legislation", "sector": "Land and soil", "sub": "Cantabria", "url": "http://www.fao.org/faolex/results/details/en/c/LEX-FAOC118896", "source": "faolex", "domain": "Land and soil", "jur": "Spain"}, {"name": "Ley Nº 2/2011 - Modifica la Ley Nº 2/2001, Ley de Ordenación Territorial y Régimen Urbanístico del Suelo de Cantabria.", "year": "2011", "type": "Legislation", "sector": "Land and soil", "sub": "Cantabria", "url": "http://www.fao.org/faolex/results/details/en/c/LEX-FAOC102457", "source": "faolex", "domain": "Land and soil", "jur": "Spain"}, {"name": "Ley Nº 6/2010 - Medidas urgentes en materia de Ordenación del Territorio y Urbanismo.", "year": "2010", "type": "Legislation", "sector": "Land and soil", "sub": "Cantabria", "url": "http://www.fao.org/faolex/results/details/en/c/LEX-FAOC118895", "source": "faolex", "domain": "Land and soil", "jur": "Spain"}, {"name": "Ley Nº 4/2006 - Ley de Conservación de la Naturaleza de Cantabria.", "year": "2006", "type": "Legislation", "sector": "Wild species and ecosystems", "sub": "Cantabria", "url": "http://www.fao.org/faolex/results/details/en/c/LEX-FAOC126288", "source": "faolex", "domain": "Wild species and ecosystems", "jur": "Spain"}, {"name": "Ley Nº 17/2006 - Ley de control ambiental integrado.", "year": "2006", "type": "Legislation", "sector": "Environment", "sub": "Cantabria", "url": "http://www.fao.org/faolex/results/details/en/c/LEX-FAOC126289", "source": "faolex", "domain": "Environment; Water", "jur": "Spain"}, {"name": "Ley Nº 2/2004 - Ley del Plan de Ordenación del Litoral.", "year": "2004", "type": "Legislation", "sector": "Environment", "sub": "Cantabria", "url": "http://www.fao.org/faolex/results/details/en/c/LEX-FAOC129703", "source": "faolex", "domain": "Environment; Land and soil; Sea", "jur": "Spain"}, {"name": "Ley Nº 2/2001 - Ley de Ordenación Territorial y Régimen Urbanístico del Suelo de Cantabria.", "year": "2001", "type": "Legislation", "sector": "Land and soil", "sub": "Cantabria", "url": "http://www.fao.org/faolex/results/details/en/c/LEX-FAOC102455", "source": "faolex", "domain": "Land and soil", "jur": "Spain"}, {"name": "Ley 4/2000, de 13 de noviembre, de Modernización y Desarrollo Agrario.", "year": "2000", "type": "Legislation", "sector": "Agricultural and rural development", "sub": "Cantabria", "url": "http://www.fao.org/faolex/results/details/en/c/LEX-FAOC238569", "source": "faolex", "domain": "Agricultural and rural development", "jur": "Spain"}, {"name": "Ley Nº 9/1994 - Usos del suelo en el medio rural.", "year": "1994", "type": "Legislation", "sector": "Land and soil", "sub": "Cantabria", "url": "http://www.fao.org/faolex/results/details/en/c/LEX-FAOC010774", "source": "faolex", "domain": "Land and soil", "jur": "Spain"}, {"name": "Ley Nº 6/1991 - Crea el Centro Regional de Investigación del Medio Ambiente.", "year": "1991", "type": "Legislation", "sector": "Environment", "sub": "Cantabria", "url": "http://www.fao.org/faolex/results/details/en/c/LEX-FAOC005521", "source": "faolex", "domain": "Environment", "jur": "Spain"}, {"name": "Ley Nº 4/1990 - Ley sobre concentración parcelaria, conservación de obras, unidades mínimas de cultivo y fomento de explotaciones rentables.", "year": "1990", "type": "Legislation", "sector": "Land and soil", "sub": "Cantabria", "url": "http://www.fao.org/faolex/results/details/en/c/LEX-FAOC003427", "source": "faolex", "domain": "Land and soil", "jur": "Spain"}, {"name": "Ley Nº 5/1990 - Ley relativa al aprovechamiento de pastos en los montes de Cantabria.", "year": "1990", "type": "Legislation", "sector": "Land and soil", "sub": "Cantabria", "url": "http://www.fao.org/faolex/results/details/en/c/LEX-FAOC003428", "source": "faolex", "domain": "Livestock; Land and soil", "jur": "Spain"}, {"name": "Ley Nº 7/1990 - Ley de ordenación territorial de Cantabria.", "year": "1990", "type": "Legislation", "sector": "Land and soil", "sub": "Cantabria", "url": "http://www.fao.org/faolex/results/details/en/c/LEX-FAOC010142", "source": "faolex", "domain": "Land and soil", "jur": "Spain"}]