[{"name": "Declaration of Disaster Emergency – COVID-19 (Executive Order 20-02 of Governor of State of Rhode Island)", "year": "2020", "type": "Regulation", "sector": "Health; Disaster risk management", "sub": "Rhode Island", "url": "http://www.fao.org/faolex/results/details/en/c/LEX-FAOC196504", "source": "faolex", "domain": "General", "jur": "United States of America"}, {"name": "Rhode Island Emergency Management Act (State of Rhode Island General Laws: Title 30 Military Affairs and Defense; Chapter 30-15)", "year": "1973", "type": "Legislation", "sector": "Disaster risk management", "sub": "Rhode Island", "url": "http://www.fao.org/faolex/results/details/en/c/LEX-FAOC196503", "source": "faolex", "domain": "Environment; General", "jur": "United States of America"}]